{"ticker":"429980","dates":["2026-07-06","2026-07-07","2026-07-08"],"snapshots":{"2026-07-06":{"ticker":"429980","snapshot_date":"2026-07-06","kpis":{"snapshot_date":"2026-07-06","holding_count":31,"total_valuation":388694050.0,"total_weight":99.62306662839121,"top_holding":{"etf_idx":"K55210DU0411","ticker":"429980","etf_name":"SOL 한국형글로벌전기차&2차전지액티브","source_url":"https://www.funetf.co.kr/product/etf/view/KR7429980006","snapshot_date":"2026-07-06","constituent_code":"TSLA US","constituent_name":"테슬라/Tesla Inc","quantity":56.12,"valuation":33685879.0,"weight":8.633758525639701}},"holdings":[{"snapshot_date":"2026-07-06","constituent_code":"TSLA US","constituent_name":"테슬라/Tesla Inc","quantity":56.12,"valuation":33685879.0,"weight":8.633758525639701},{"snapshot_date":"2026-07-06","constituent_code":"AMD US","constituent_name":"Advanced Micro Devices Inc","quantity":31.28,"valuation":24710768.0,"weight":6.333419528553929},{"snapshot_date":"2026-07-06","constituent_code":"005930","constituent_name":"삼성전자","quantity":76.0,"valuation":23522000.0,"weight":6.028735899695449},{"snapshot_date":"2026-07-06","constituent_code":"IFX GR","constituent_name":"Infineon Technologies AG","quantity":167.76,"valuation":22211723.0,"weight":5.6929092697981085},{"snapshot_date":"2026-07-06","constituent_code":"STMPA FP","constituent_name":"STMicroelectronics NV","quantity":196.68,"valuation":21264519.0,"weight":5.450138979893546},{"snapshot_date":"2026-07-06","constituent_code":"1211 HK","constituent_name":"BYD COMPANY LTD","quantity":1126.52,"valuation":17157931.0,"weight":4.39761221767696},{"snapshot_date":"2026-07-06","constituent_code":"QCOM US","constituent_name":"QUALCOMM Inc","quantity":63.72,"valuation":17133479.0,"weight":4.391345120907155},{"snapshot_date":"2026-07-06","constituent_code":"NVDA US","constituent_name":"엔비디아/NVIDIA Corp","quantity":56.84,"valuation":16894703.0,"weight":4.330146351959544},{"snapshot_date":"2026-07-06","constituent_code":"ETN US","constituent_name":"Eaton Corp plc","quantity":26.52,"valuation":16123685.0,"weight":4.132532888142208},{"snapshot_date":"2026-07-06","constituent_code":"NXPI US","constituent_name":"NXP Semiconductors NV","quantity":38.2,"valuation":15930852.0,"weight":4.083109402480021},{"snapshot_date":"2026-07-06","constituent_code":"ON US","constituent_name":"ON SEMICONDUCTOR CORP","quantity":109.48,"valuation":15235809.0,"weight":3.9049684839385694},{"snapshot_date":"2026-07-06","constituent_code":"QQQ US","constituent_name":"POWERSHARES QQQ NASDAQ 100","quantity":13.34,"valuation":14502481.0,"weight":3.7170150429109414},{"snapshot_date":"2026-07-06","constituent_code":"ABB SS","constituent_name":"ABB LTD-REG","quantity":89.32,"valuation":14443915.0,"weight":3.7020044593423007},{"snapshot_date":"2026-07-06","constituent_code":"012330","constituent_name":"현대모비스","quantity":28.0,"valuation":13832000.0,"weight":3.5451694143604904},{"snapshot_date":"2026-07-06","constituent_code":"006400","constituent_name":"삼성SDI","quantity":29.0,"valuation":13557500.0,"weight":3.4748145123765433},{"snapshot_date":"2026-07-06","constituent_code":"LITE US","constituent_name":"루멘텀/Lumentum Holdings Inc","quantity":11.88,"valuation":13200164.0,"weight":3.3832285770201294},{"snapshot_date":"2026-07-06","constituent_code":"US4380908057","constituent_name":"Hon Hai Precision-GDR REG S","quantity":569.08,"valuation":12690744.0,"weight":3.252663206642489},{"snapshot_date":"2026-07-06","constituent_code":"373220","constituent_name":"LG에너지솔루션","quantity":23.0,"valuation":8337500.0,"weight":2.1369180156326335},{"snapshot_date":"2026-07-06","constituent_code":"MG CN","constituent_name":"Magna International Inc","quantity":81.36,"valuation":7783179.0,"weight":1.9948444286648979},{"snapshot_date":"2026-07-06","constituent_code":"086520","constituent_name":"에코프로","quantity":87.0,"valuation":7595100.0,"weight":1.9466394027623888},{"snapshot_date":"2026-07-06","constituent_code":"5801 JP","constituent_name":"Furukawa Electric Co Ltd","quantity":198.8,"valuation":7502750.0,"weight":1.9229699120584998},{"snapshot_date":"2026-07-06","constituent_code":"3750 HK","constituent_name":"Contemporary Amperex Technology Co Ltd","quantity":54.48,"valuation":7216863.0,"weight":1.8496964990767706},{"snapshot_date":"2026-07-06","constituent_code":"RIVN US","constituent_name":"Rivian Automotive Inc","quantity":252.28,"valuation":7170283.0,"weight":1.8377579514104236},{"snapshot_date":"2026-07-06","constituent_code":"HEXAB SS","constituent_name":"Hexagon AB-B","quantity":517.8,"valuation":6711150.0,"weight":1.7200812402534271},{"snapshot_date":"2026-07-06","constituent_code":"APTV US","constituent_name":"Aptiv plc","quantity":64.84,"valuation":5825393.0,"weight":1.4930599400108229},{"snapshot_date":"2026-07-06","constituent_code":"300014 C2","constituent_name":"Eve Energy Co Ltd","quantity":325.96,"valuation":4494801.0,"weight":1.152026534762648},{"snapshot_date":"2026-07-06","constituent_code":"066970","constituent_name":"엘앤에프","quantity":42.0,"valuation":4452000.0,"weight":1.1410565523953806},{"snapshot_date":"2026-07-06","constituent_code":"9868 HK","constituent_name":"Xpeng inc","quantity":427.4,"valuation":4306540.0,"weight":1.1037748618941603},{"snapshot_date":"2026-07-06","constituent_code":"9866 HK","constituent_name":"NIO Inc","quantity":561.68,"valuation":4103730.0,"weight":1.0517942510695182},{"snapshot_date":"2026-07-06","constituent_code":"006260","constituent_name":"LS","quantity":10.0,"valuation":3740000.0,"weight":0.9585695206555982},{"snapshot_date":"2026-07-06","constituent_code":"2015 HK","constituent_name":"Li Auto Inc","quantity":368.4,"valuation":3356609.0,"weight":0.8603056364059537}],"top_changes":{"additions":[],"removals":[],"weight_changes":[{"snapshot_date":"2026-07-06","previous_snapshot_date":"2026-07-03","change_type":"비중확대","constituent_code":"005930","constituent_name":"삼성전자","previous_weight":5.390022937602673,"weight":6.028735899695449,"weight_delta":0.6387129620927761,"active_signal_ratio":1.0,"active_change_type":"drift"},{"snapshot_date":"2026-07-06","previous_snapshot_date":"2026-07-03","change_type":"비중축소","constituent_code":"TSLA US","constituent_name":"테슬라/Tesla Inc","previous_weight":9.208264748126654,"weight":8.633758525639701,"weight_delta":-0.5745062224869528,"active_signal_ratio":1.0,"active_change_type":"drift"},{"snapshot_date":"2026-07-06","previous_snapshot_date":"2026-07-03","change_type":"비중확대","constituent_code":"1211 HK","constituent_name":"BYD COMPANY LTD","previous_weight":4.014398374026279,"weight":4.39761221767696,"weight_delta":0.38321384365068045,"active_signal_ratio":1.0,"active_change_type":"drift"},{"snapshot_date":"2026-07-06","previous_snapshot_date":"2026-07-03","change_type":"비중축소","constituent_code":"LITE US","constituent_name":"루멘텀/Lumentum Holdings Inc","previous_weight":3.671981147616129,"weight":3.3832285770201294,"weight_delta":-0.28875257059599946,"active_signal_ratio":1.0,"active_change_type":"drift"},{"snapshot_date":"2026-07-06","previous_snapshot_date":"2026-07-03","change_type":"비중축소","constituent_code":"AMD US","constituent_name":"Advanced Micro Devices Inc","previous_weight":6.52728256473638,"weight":6.333419528553929,"weight_delta":-0.19386303618245115,"active_signal_ratio":1.0,"active_change_type":"drift"},{"snapshot_date":"2026-07-06","previous_snapshot_date":"2026-07-03","change_type":"비중확대","constituent_code":"RIVN US","constituent_name":"Rivian Automotive Inc","previous_weight":1.6721326118234479,"weight":1.8377579514104236,"weight_delta":0.16562533958697578,"active_signal_ratio":1.0,"active_change_type":"drift"},{"snapshot_date":"2026-07-06","previous_snapshot_date":"2026-07-03","change_type":"비중축소","constituent_code":"5801 JP","constituent_name":"Furukawa Electric Co Ltd","previous_weight":2.0577114338539713,"weight":1.9229699120584998,"weight_delta":-0.1347415217954715,"active_signal_ratio":1.0,"active_change_type":"drift"},{"snapshot_date":"2026-07-06","previous_snapshot_date":"2026-07-03","change_type":"비중확대","constituent_code":"012330","constituent_name":"현대모비스","previous_weight":3.4161278978843588,"weight":3.5451694143604904,"weight_delta":0.1290415164761316,"active_signal_ratio":1.0,"active_change_type":"drift"}]}},"2026-07-07":{"ticker":"429980","snapshot_date":"2026-07-07","kpis":{"snapshot_date":"2026-07-07","holding_count":31,"total_valuation":392317171.0,"total_weight":99.61656613502187,"top_holding":{"etf_idx":"K55210DU0411","ticker":"429980","etf_name":"SOL 한국형글로벌전기차&2차전지액티브","source_url":"https://www.funetf.co.kr/product/etf/view/KR7429980006","snapshot_date":"2026-07-07","constituent_code":"TSLA US","constituent_name":"테슬라/Tesla Inc","quantity":56.12,"valuation":33789657.0,"weight":8.579817173539428}},"holdings":[{"snapshot_date":"2026-07-07","constituent_code":"TSLA US","constituent_name":"테슬라/Tesla Inc","quantity":56.12,"valuation":33789657.0,"weight":8.579817173539428},{"snapshot_date":"2026-07-07","constituent_code":"AMD US","constituent_name":"Advanced Micro Devices Inc","quantity":31.28,"valuation":24786895.0,"weight":6.293849842859269},{"snapshot_date":"2026-07-07","constituent_code":"005930","constituent_name":"삼성전자","quantity":76.0,"valuation":24168000.0,"weight":6.136700986639223},{"snapshot_date":"2026-07-07","constituent_code":"IFX GR","constituent_name":"Infineon Technologies AG","quantity":167.76,"valuation":22754722.0,"weight":5.777843634065758},{"snapshot_date":"2026-07-07","constituent_code":"STMPA FP","constituent_name":"STMicroelectronics NV","quantity":196.68,"valuation":21584682.0,"weight":5.480748896296502},{"snapshot_date":"2026-07-07","constituent_code":"1211 HK","constituent_name":"BYD COMPANY LTD","quantity":1126.52,"valuation":18486680.0,"weight":4.694109044839606},{"snapshot_date":"2026-07-07","constituent_code":"QCOM US","constituent_name":"QUALCOMM Inc","quantity":63.72,"valuation":17186263.0,"weight":4.36390918192408},{"snapshot_date":"2026-07-07","constituent_code":"NVDA US","constituent_name":"엔비디아/NVIDIA Corp","quantity":56.84,"valuation":16946752.0,"weight":4.3030929211656},{"snapshot_date":"2026-07-07","constituent_code":"ETN US","constituent_name":"Eaton Corp plc","quantity":26.52,"valuation":16173358.0,"weight":4.106713919061129},{"snapshot_date":"2026-07-07","constituent_code":"NXPI US","constituent_name":"NXP Semiconductors NV","quantity":38.2,"valuation":15979931.0,"weight":4.057599235937054},{"snapshot_date":"2026-07-07","constituent_code":"ON US","constituent_name":"ON SEMICONDUCTOR CORP","quantity":109.48,"valuation":15282747.0,"weight":3.880571358550878},{"snapshot_date":"2026-07-07","constituent_code":"ABB SS","constituent_name":"ABB LTD-REG","quantity":89.32,"valuation":14833143.0,"weight":3.7664086098585186},{"snapshot_date":"2026-07-07","constituent_code":"QQQ US","constituent_name":"POWERSHARES QQQ NASDAQ 100","quantity":13.34,"valuation":14547160.0,"weight":3.6937922511088477},{"snapshot_date":"2026-07-07","constituent_code":"012330","constituent_name":"현대모비스","quantity":28.0,"valuation":14420000.0,"weight":3.661503981601191},{"snapshot_date":"2026-07-07","constituent_code":"LITE US","constituent_name":"루멘텀/Lumentum Holdings Inc","quantity":11.88,"valuation":13240831.0,"weight":3.362091222344555},{"snapshot_date":"2026-07-07","constituent_code":"006400","constituent_name":"삼성SDI","quantity":29.0,"valuation":13093500.0,"weight":3.3246811638762273},{"snapshot_date":"2026-07-07","constituent_code":"US4380908057","constituent_name":"Hon Hai Precision-GDR REG S","quantity":569.08,"valuation":12729841.0,"weight":3.2323414359674127},{"snapshot_date":"2026-07-07","constituent_code":"373220","constituent_name":"LG에너지솔루션","quantity":23.0,"valuation":8153500.0,"weight":2.0703240439656945},{"snapshot_date":"2026-07-07","constituent_code":"MG CN","constituent_name":"Magna International Inc","quantity":81.36,"valuation":7914032.0,"weight":2.0095187017003635},{"snapshot_date":"2026-07-07","constituent_code":"5801 JP","constituent_name":"Furukawa Electric Co Ltd","quantity":198.8,"valuation":7506369.0,"weight":1.9060055465234225},{"snapshot_date":"2026-07-07","constituent_code":"086520","constituent_name":"에코프로","quantity":87.0,"valuation":7438500.0,"weight":1.888772355557591},{"snapshot_date":"2026-07-07","constituent_code":"RIVN US","constituent_name":"Rivian Automotive Inc","quantity":252.28,"valuation":7192373.0,"weight":1.826276170364834},{"snapshot_date":"2026-07-07","constituent_code":"3750 HK","constituent_name":"Contemporary Amperex Technology Co Ltd","quantity":54.48,"valuation":7181025.0,"weight":1.8233947038472742},{"snapshot_date":"2026-07-07","constituent_code":"HEXAB SS","constituent_name":"Hexagon AB-B","quantity":517.8,"valuation":6793077.0,"weight":1.724887550819936},{"snapshot_date":"2026-07-07","constituent_code":"APTV US","constituent_name":"Aptiv plc","quantity":64.84,"valuation":5843339.0,"weight":1.4837315543928935},{"snapshot_date":"2026-07-07","constituent_code":"300014 C2","constituent_name":"Eve Energy Co Ltd","quantity":325.96,"valuation":4493111.0,"weight":1.1408837597972337},{"snapshot_date":"2026-07-07","constituent_code":"066970","constituent_name":"엘앤에프","quantity":42.0,"valuation":4342800.0,"weight":1.1027170243618345},{"snapshot_date":"2026-07-07","constituent_code":"9868 HK","constituent_name":"Xpeng inc","quantity":427.4,"valuation":4311705.0,"weight":1.094821430304422},{"snapshot_date":"2026-07-07","constituent_code":"9866 HK","constituent_name":"NIO Inc","quantity":561.68,"valuation":4208663.0,"weight":1.0686571658611383},{"snapshot_date":"2026-07-07","constituent_code":"006260","constituent_name":"LS","quantity":10.0,"valuation":3530000.0,"weight":0.8963321120008464},{"snapshot_date":"2026-07-07","constituent_code":"2015 HK","constituent_name":"Li Auto Inc","quantity":368.4,"valuation":3404515.0,"weight":0.864469155889111}],"top_changes":{"additions":[],"removals":[],"weight_changes":[{"snapshot_date":"2026-07-07","previous_snapshot_date":"2026-07-06","change_type":"비중확대","constituent_code":"1211 HK","constituent_name":"BYD COMPANY LTD","previous_weight":4.39761221767696,"weight":4.694109044839606,"weight_delta":0.29649682716264625,"active_signal_ratio":1.0,"active_change_type":"drift"},{"snapshot_date":"2026-07-07","previous_snapshot_date":"2026-07-06","change_type":"비중축소","constituent_code":"006400","constituent_name":"삼성SDI","previous_weight":3.4748145123765433,"weight":3.3246811638762273,"weight_delta":-0.150133348500316,"active_signal_ratio":1.0,"active_change_type":"drift"},{"snapshot_date":"2026-07-07","previous_snapshot_date":"2026-07-06","change_type":"비중확대","constituent_code":"012330","constituent_name":"현대모비스","previous_weight":3.5451694143604904,"weight":3.661503981601191,"weight_delta":0.11633456724070079,"active_signal_ratio":1.0,"active_change_type":"drift"},{"snapshot_date":"2026-07-07","previous_snapshot_date":"2026-07-06","change_type":"비중확대","constituent_code":"005930","constituent_name":"삼성전자","previous_weight":6.028735899695449,"weight":6.136700986639223,"weight_delta":0.10796508694377405,"active_signal_ratio":1.0,"active_change_type":"drift"},{"snapshot_date":"2026-07-07","previous_snapshot_date":"2026-07-06","change_type":"비중확대","constituent_code":"IFX GR","constituent_name":"Infineon Technologies AG","previous_weight":5.6929092697981085,"weight":5.777843634065758,"weight_delta":0.08493436426764944,"active_signal_ratio":1.0,"active_change_type":"drift"},{"snapshot_date":"2026-07-07","previous_snapshot_date":"2026-07-06","change_type":"비중축소","constituent_code":"373220","constituent_name":"LG에너지솔루션","previous_weight":2.1369180156326335,"weight":2.0703240439656945,"weight_delta":-0.06659397166693903,"active_signal_ratio":1.0,"active_change_type":"drift"},{"snapshot_date":"2026-07-07","previous_snapshot_date":"2026-07-06","change_type":"비중확대","constituent_code":"ABB SS","constituent_name":"ABB LTD-REG","previous_weight":3.7020044593423007,"weight":3.7664086098585186,"weight_delta":0.06440415051621784,"active_signal_ratio":1.0,"active_change_type":"drift"},{"snapshot_date":"2026-07-07","previous_snapshot_date":"2026-07-06","change_type":"비중축소","constituent_code":"006260","constituent_name":"LS","previous_weight":0.9585695206555982,"weight":0.8963321120008464,"weight_delta":-0.0622374086547518,"active_signal_ratio":1.0,"active_change_type":"drift"}]}},"2026-07-08":{"ticker":"429980","snapshot_date":"2026-07-08","kpis":{"snapshot_date":"2026-07-08","holding_count":31,"total_valuation":396364854.0,"total_weight":99.64303688738995,"top_holding":{"etf_idx":"K55210DU0411","ticker":"429980","etf_name":"SOL 한국형글로벌전기차&2차전지액티브","source_url":"https://www.funetf.co.kr/product/etf/view/KR7429980006","snapshot_date":"2026-07-08","constituent_code":"TSLA US","constituent_name":"테슬라/Tesla Inc","quantity":56.12,"valuation":36000559.0,"weight":9.050260113132177}},"holdings":[{"snapshot_date":"2026-07-08","constituent_code":"TSLA US","constituent_name":"테슬라/Tesla Inc","quantity":56.12,"valuation":36000559.0,"weight":9.050260113132177},{"snapshot_date":"2026-07-08","constituent_code":"AMD US","constituent_name":"Advanced Micro Devices Inc","quantity":31.28,"valuation":26389147.0,"weight":6.634026002587394},{"snapshot_date":"2026-07-08","constituent_code":"005930","constituent_name":"삼성전자","quantity":76.0,"valuation":22496000.0,"weight":5.655319171711235},{"snapshot_date":"2026-07-08","constituent_code":"IFX GR","constituent_name":"Infineon Technologies AG","quantity":167.76,"valuation":22477539.0,"weight":5.650678220109663},{"snapshot_date":"2026-07-08","constituent_code":"STMPA FP","constituent_name":"STMicroelectronics NV","quantity":196.68,"valuation":21804045.0,"weight":5.4813670745623435},{"snapshot_date":"2026-07-08","constituent_code":"1211 HK","constituent_name":"BYD COMPANY LTD","quantity":1126.52,"valuation":18395246.0,"weight":4.624421558150089},{"snapshot_date":"2026-07-08","constituent_code":"QCOM US","constituent_name":"QUALCOMM Inc","quantity":63.72,"valuation":18158845.0,"weight":4.564992188150458},{"snapshot_date":"2026-07-08","constituent_code":"NVDA US","constituent_name":"엔비디아/NVIDIA Corp","quantity":56.84,"valuation":16986037.0,"weight":4.270157392314029},{"snapshot_date":"2026-07-08","constituent_code":"ETN US","constituent_name":"Eaton Corp plc","quantity":26.52,"valuation":16755029.0,"weight":4.2120837805066556},{"snapshot_date":"2026-07-08","constituent_code":"NXPI US","constituent_name":"NXP Semiconductors NV","quantity":38.2,"valuation":16375399.0,"weight":4.116647755561921},{"snapshot_date":"2026-07-08","constituent_code":"ON US","constituent_name":"ON SEMICONDUCTOR CORP","quantity":109.48,"valuation":15842331.0,"weight":3.9826386125931372},{"snapshot_date":"2026-07-08","constituent_code":"ABB SS","constituent_name":"ABB LTD-REG","quantity":89.32,"valuation":14747958.0,"weight":3.7075217648022796},{"snapshot_date":"2026-07-08","constituent_code":"QQQ US","constituent_name":"POWERSHARES QQQ NASDAQ 100","quantity":13.34,"valuation":14735544.0,"weight":3.704400981898758},{"snapshot_date":"2026-07-08","constituent_code":"012330","constituent_name":"현대모비스","quantity":28.0,"valuation":13860000.0,"weight":3.484296040181264},{"snapshot_date":"2026-07-08","constituent_code":"US4380908057","constituent_name":"Hon Hai Precision-GDR REG S","quantity":569.08,"valuation":13366798.0,"weight":3.3603088990838987},{"snapshot_date":"2026-07-08","constituent_code":"LITE US","constituent_name":"루멘텀/Lumentum Holdings Inc","quantity":11.88,"valuation":13275855.0,"weight":3.337446537267001},{"snapshot_date":"2026-07-08","constituent_code":"006400","constituent_name":"삼성SDI","quantity":29.0,"valuation":12905000.0,"weight":3.244216478971083},{"snapshot_date":"2026-07-08","constituent_code":"MG CN","constituent_name":"Magna International Inc","quantity":81.36,"valuation":8157732.0,"weight":2.0507902817070693},{"snapshot_date":"2026-07-08","constituent_code":"RIVN US","constituent_name":"Rivian Automotive Inc","quantity":252.28,"valuation":7764660.0,"weight":1.9519750426662232},{"snapshot_date":"2026-07-08","constituent_code":"373220","constituent_name":"LG에너지솔루션","quantity":23.0,"valuation":7636000.0,"weight":1.919630920838682},{"snapshot_date":"2026-07-08","constituent_code":"086520","constituent_name":"에코프로","quantity":87.0,"valuation":7342800.0,"weight":1.845922724663996},{"snapshot_date":"2026-07-08","constituent_code":"5801 JP","constituent_name":"Furukawa Electric Co Ltd","quantity":198.8,"valuation":7291090.0,"weight":1.8329232334491494},{"snapshot_date":"2026-07-08","constituent_code":"3750 HK","constituent_name":"Contemporary Amperex Technology Co Ltd","quantity":54.48,"valuation":7091469.0,"weight":1.7827400689587436},{"snapshot_date":"2026-07-08","constituent_code":"HEXAB SS","constituent_name":"Hexagon AB-B","quantity":517.8,"valuation":6695799.0,"weight":1.6832717129545214},{"snapshot_date":"2026-07-08","constituent_code":"APTV US","constituent_name":"Aptiv plc","quantity":64.84,"valuation":5918555.0,"weight":1.4878786255479812},{"snapshot_date":"2026-07-08","constituent_code":"9868 HK","constituent_name":"Xpeng inc","quantity":427.4,"valuation":4401515.0,"weight":1.1065065862408683},{"snapshot_date":"2026-07-08","constituent_code":"300014 C2","constituent_name":"Eve Energy Co Ltd","quantity":325.96,"valuation":4350578.0,"weight":1.0937014212048861},{"snapshot_date":"2026-07-08","constituent_code":"9866 HK","constituent_name":"NIO Inc","quantity":561.68,"valuation":4233485.0,"weight":1.064265153078411},{"snapshot_date":"2026-07-08","constituent_code":"066970","constituent_name":"엘앤에프","quantity":42.0,"valuation":4179000.0,"weight":1.0505680484788962},{"snapshot_date":"2026-07-08","constituent_code":"006260","constituent_name":"LS","quantity":10.0,"valuation":3410000.0,"weight":0.8572474384572951},{"snapshot_date":"2026-07-08","constituent_code":"2015 HK","constituent_name":"Li Auto Inc","quantity":368.4,"valuation":3320839.0,"weight":0.834833057559849}],"top_changes":{"additions":[],"removals":[],"weight_changes":[{"snapshot_date":"2026-07-08","previous_snapshot_date":"2026-07-07","change_type":"비중축소","constituent_code":"005930","constituent_name":"삼성전자","previous_weight":6.136700986639223,"weight":5.655319171711235,"weight_delta":-0.48138181492798804,"active_signal_ratio":1.0,"active_change_type":"drift"},{"snapshot_date":"2026-07-08","previous_snapshot_date":"2026-07-07","change_type":"비중확대","constituent_code":"TSLA US","constituent_name":"테슬라/Tesla Inc","previous_weight":8.579817173539428,"weight":9.050260113132177,"weight_delta":0.47044293959274874,"active_signal_ratio":1.0,"active_change_type":"drift"},{"snapshot_date":"2026-07-08","previous_snapshot_date":"2026-07-07","change_type":"비중확대","constituent_code":"AMD US","constituent_name":"Advanced Micro Devices Inc","previous_weight":6.293849842859269,"weight":6.634026002587394,"weight_delta":0.34017615972812454,"active_signal_ratio":1.0,"active_change_type":"drift"},{"snapshot_date":"2026-07-08","previous_snapshot_date":"2026-07-07","change_type":"비중확대","constituent_code":"QCOM US","constituent_name":"QUALCOMM Inc","previous_weight":4.36390918192408,"weight":4.564992188150458,"weight_delta":0.2010830062263782,"active_signal_ratio":1.0,"active_change_type":"drift"},{"snapshot_date":"2026-07-08","previous_snapshot_date":"2026-07-07","change_type":"비중축소","constituent_code":"012330","constituent_name":"현대모비스","previous_weight":3.661503981601191,"weight":3.484296040181264,"weight_delta":-0.17720794141992702,"active_signal_ratio":1.0,"active_change_type":"drift"},{"snapshot_date":"2026-07-08","previous_snapshot_date":"2026-07-07","change_type":"비중축소","constituent_code":"373220","constituent_name":"LG에너지솔루션","previous_weight":2.0703240439656945,"weight":1.919630920838682,"weight_delta":-0.15069312312701255,"active_signal_ratio":1.0,"active_change_type":"drift"},{"snapshot_date":"2026-07-08","previous_snapshot_date":"2026-07-07","change_type":"비중확대","constituent_code":"US4380908057","constituent_name":"Hon Hai Precision-GDR REG S","previous_weight":3.2323414359674127,"weight":3.3603088990838987,"weight_delta":0.127967463116486,"active_signal_ratio":1.0,"active_change_type":"drift"},{"snapshot_date":"2026-07-08","previous_snapshot_date":"2026-07-07","change_type":"비중축소","constituent_code":"IFX GR","constituent_name":"Infineon Technologies AG","previous_weight":5.777843634065758,"weight":5.650678220109663,"weight_delta":-0.12716541395609493,"active_signal_ratio":1.0,"active_change_type":"drift"}]}}}}
