{"ticker":"0192S0","dates":["2026-07-09","2026-07-10","2026-07-13"],"snapshots":{"2026-07-09":{"ticker":"0192S0","snapshot_date":"2026-07-09","kpis":{"snapshot_date":"2026-07-09","holding_count":186,"total_valuation":408723360.0,"total_weight":41.89546798885676,"top_holding":{"etf_idx":"K55210EU9643","ticker":"0192S0","etf_name":"SOL 코스피200채권혼합50","source_url":"https://www.funetf.co.kr/product/etf/view/KR70192S0000","snapshot_date":"2026-07-09","constituent_code":"005930","constituent_name":"삼성전자","quantity":485.0,"valuation":134587500.0,"weight":13.795654591287024}},"holdings":[{"snapshot_date":"2026-07-09","constituent_code":"005930","constituent_name":"삼성전자","quantity":485.0,"valuation":134587500.0,"weight":13.795654591287024},{"snapshot_date":"2026-07-09","constituent_code":"000660","constituent_name":"SK하이닉스","quantity":58.0,"valuation":120408000.0,"weight":12.342209923118327},{"snapshot_date":"2026-07-09","constituent_code":"402340","constituent_name":"SK스퀘어","quantity":9.0,"valuation":11430000.0,"weight":1.1716120143283044},{"snapshot_date":"2026-07-09","constituent_code":"009150","constituent_name":"삼성전기","quantity":6.0,"valuation":8874000.0,"weight":0.9096137371084316},{"snapshot_date":"2026-07-09","constituent_code":"005380","constituent_name":"현대차","quantity":14.0,"valuation":6475000.0,"weight":0.6637084683093414},{"snapshot_date":"2026-07-09","constituent_code":"105560","constituent_name":"KB금융","quantity":31.0,"valuation":5301000.0,"weight":0.5433696664876939},{"snapshot_date":"2026-07-09","constituent_code":"055550","constituent_name":"신한지주","quantity":43.0,"valuation":4613900.0,"weight":0.47293969141814207},{"snapshot_date":"2026-07-09","constituent_code":"000270","constituent_name":"기아","quantity":26.0,"valuation":4076800.0,"weight":0.41788520210093016},{"snapshot_date":"2026-07-09","constituent_code":"028260","constituent_name":"삼성물산","quantity":10.0,"valuation":3950000.0,"weight":0.40488779147828546},{"snapshot_date":"2026-07-09","constituent_code":"012330","constituent_name":"현대모비스","quantity":7.0,"valuation":3419500.0,"weight":0.3505098235341765},{"snapshot_date":"2026-07-09","constituent_code":"034020","constituent_name":"두산에너빌리티","quantity":45.0,"valuation":3330000.0,"weight":0.34133578370194695},{"snapshot_date":"2026-07-09","constituent_code":"086790","constituent_name":"하나금융지주","quantity":26.0,"valuation":3179800.0,"weight":0.32593979730193723},{"snapshot_date":"2026-07-09","constituent_code":"012450","constituent_name":"한화에어로스페이스","quantity":3.0,"valuation":3123000.0,"weight":0.32011761336371786},{"snapshot_date":"2026-07-09","constituent_code":"032830","constituent_name":"삼성생명","quantity":9.0,"valuation":3114000.0,"weight":0.31919508421857745},{"snapshot_date":"2026-07-09","constituent_code":"068270","constituent_name":"셀트리온","quantity":16.0,"valuation":2828800.0,"weight":0.2899611606414617},{"snapshot_date":"2026-07-09","constituent_code":"035420","constituent_name":"네이버/NAVER","quantity":14.0,"valuation":2697800.0,"weight":0.2765332364177515},{"snapshot_date":"2026-07-09","constituent_code":"298040","constituent_name":"효성중공업","quantity":1.0,"valuation":2689000.0,"weight":0.2756312079202809},{"snapshot_date":"2026-07-09","constituent_code":"006400","constituent_name":"삼성SDI","quantity":6.0,"valuation":2472000.0,"weight":0.2533880051985624},{"snapshot_date":"2026-07-09","constituent_code":"267260","constituent_name":"HD현대일렉트릭","quantity":3.0,"valuation":2442000.0,"weight":0.2503129080480944},{"snapshot_date":"2026-07-09","constituent_code":"066570","constituent_name":"LG전자","quantity":11.0,"valuation":2153800.0,"weight":0.22077147475593195},{"snapshot_date":"2026-07-09","constituent_code":"316140","constituent_name":"우리금융지주","quantity":70.0,"valuation":2149000.0,"weight":0.22027945921185707},{"snapshot_date":"2026-07-09","constituent_code":"005490","constituent_name":"POSCO홀딩스/포스코홀딩스","quantity":7.0,"valuation":2128000.0,"weight":0.21812689120652948},{"snapshot_date":"2026-07-09","constituent_code":"000810","constituent_name":"삼성화재","quantity":3.0,"valuation":2013000.0,"weight":0.20633901879640218},{"snapshot_date":"2026-07-09","constituent_code":"034730","constituent_name":"SK","quantity":3.0,"valuation":1788000.0,"weight":0.18327579016789225},{"snapshot_date":"2026-07-09","constituent_code":"009540","constituent_name":"HD한국조선해양","quantity":5.0,"valuation":1700000.0,"weight":0.17425550519318614},{"snapshot_date":"2026-07-09","constituent_code":"033780","constituent_name":"KT&G","quantity":9.0,"valuation":1658700.0,"weight":0.1700221214493752},{"snapshot_date":"2026-07-09","constituent_code":"010120","constituent_name":"LS ELECTRIC","quantity":9.0,"valuation":1651500.0,"weight":0.1692840981332629},{"snapshot_date":"2026-07-09","constituent_code":"373220","constituent_name":"LG에너지솔루션","quantity":5.0,"valuation":1577500.0,"weight":0.16169885849544186},{"snapshot_date":"2026-07-09","constituent_code":"329180","constituent_name":"HD현대중공업","quantity":3.0,"valuation":1551000.0,"weight":0.15898252267919513},{"snapshot_date":"2026-07-09","constituent_code":"011070","constituent_name":"LG이노텍","quantity":2.0,"valuation":1526000.0,"weight":0.1564199417204718},{"snapshot_date":"2026-07-09","constituent_code":"010140","constituent_name":"삼성중공업","quantity":69.0,"valuation":1459350.0,"weight":0.1495881008845154},{"snapshot_date":"2026-07-09","constituent_code":"079550","constituent_name":"LIG디펜스앤에어로스페이스","quantity":2.0,"valuation":1428000.0,"weight":0.14637462436227636},{"snapshot_date":"2026-07-09","constituent_code":"207940","constituent_name":"삼성바이오로직스","quantity":1.0,"valuation":1363000.0,"weight":0.13971191386959572},{"snapshot_date":"2026-07-09","constituent_code":"064350","constituent_name":"현대로템","quantity":8.0,"valuation":1352800.0,"weight":0.1386663808384366},{"snapshot_date":"2026-07-09","constituent_code":"051910","constituent_name":"LG화학","quantity":5.0,"valuation":1275000.0,"weight":0.1306916288948896},{"snapshot_date":"2026-07-09","constituent_code":"030200","constituent_name":"KT","quantity":23.0,"valuation":1274200.0,"weight":0.13060962630421047},{"snapshot_date":"2026-07-09","constituent_code":"000150","constituent_name":"두산","quantity":1.0,"valuation":1268000.0,"weight":0.12997410622644706},{"snapshot_date":"2026-07-09","constituent_code":"017670","constituent_name":"SK텔레콤","quantity":15.0,"valuation":1260000.0,"weight":0.1291540803196556},{"snapshot_date":"2026-07-09","constituent_code":"035720","constituent_name":"카카오","quantity":35.0,"valuation":1212750.0,"weight":0.12431080230766853},{"snapshot_date":"2026-07-09","constituent_code":"015760","constituent_name":"한국전력","quantity":33.0,"valuation":1212750.0,"weight":0.12431080230766853},{"snapshot_date":"2026-07-09","constituent_code":"278470","constituent_name":"에이피알","quantity":3.0,"valuation":1156500.0,"weight":0.11854499515054104},{"snapshot_date":"2026-07-09","constituent_code":"042660","constituent_name":"한화오션","quantity":14.0,"valuation":1148000.0,"weight":0.11767371762457511},{"snapshot_date":"2026-07-09","constituent_code":"047810","constituent_name":"한국항공우주","quantity":8.0,"valuation":1136000.0,"weight":0.11644367876438791},{"snapshot_date":"2026-07-09","constituent_code":"006800","constituent_name":"미래에셋증권","quantity":28.0,"valuation":1134000.0,"weight":0.11623867228769005},{"snapshot_date":"2026-07-09","constituent_code":"010130","constituent_name":"고려아연","quantity":1.0,"valuation":1034000.0,"weight":0.10598834845279674},{"snapshot_date":"2026-07-09","constituent_code":"267250","constituent_name":"HD현대","quantity":5.0,"valuation":968500.0,"weight":0.09927438634094163},{"snapshot_date":"2026-07-09","constituent_code":"071050","constituent_name":"한국금융지주","quantity":4.0,"valuation":934000.0,"weight":0.09573802461790344},{"snapshot_date":"2026-07-09","constituent_code":"003550","constituent_name":"LG","quantity":9.0,"valuation":922500.0,"weight":0.09455923737689072},{"snapshot_date":"2026-07-09","constituent_code":"138040","constituent_name":"메리츠금융지주","quantity":8.0,"valuation":909600.0,"weight":0.09323694560218948},{"snapshot_date":"2026-07-09","constituent_code":"000720","constituent_name":"현대건설","quantity":8.0,"valuation":805600.0,"weight":0.08257660881390044},{"snapshot_date":"2026-07-09","constituent_code":"096770","constituent_name":"SK이노베이션","quantity":8.0,"valuation":798400.0,"weight":0.08183858549778812},{"snapshot_date":"2026-07-09","constituent_code":"042700","constituent_name":"한미반도체","quantity":4.0,"valuation":796800.0,"weight":0.08167458031642984},{"snapshot_date":"2026-07-09","constituent_code":"323410","constituent_name":"카카오뱅크","quantity":36.0,"valuation":792000.0,"weight":0.08118256477235496},{"snapshot_date":"2026-07-09","constituent_code":"018260","constituent_name":"삼성에스디에스","quantity":4.0,"valuation":777200.0,"weight":0.07966551684479074},{"snapshot_date":"2026-07-09","constituent_code":"086280","constituent_name":"현대글로비스","quantity":4.0,"valuation":761600.0,"weight":0.07806646632654739},{"snapshot_date":"2026-07-09","constituent_code":"259960","constituent_name":"크래프톤","quantity":3.0,"valuation":735000.0,"weight":0.07533988018646577},{"snapshot_date":"2026-07-09","constituent_code":"003490","constituent_name":"대한항공","quantity":26.0,"valuation":731900.0,"weight":0.07502212014758408},{"snapshot_date":"2026-07-09","constituent_code":"028050","constituent_name":"삼성E&A","quantity":16.0,"valuation":696000.0,"weight":0.07134225389085738},{"snapshot_date":"2026-07-09","constituent_code":"352820","constituent_name":"하이브","quantity":3.0,"valuation":690000.0,"weight":0.07072723446076379},{"snapshot_date":"2026-07-09","constituent_code":"180640","constituent_name":"한진칼","quantity":5.0,"valuation":680500.0,"weight":0.06975345369644892},{"snapshot_date":"2026-07-09","constituent_code":"016360","constituent_name":"삼성증권","quantity":6.0,"valuation":670200.0,"weight":0.06869767034145491},{"snapshot_date":"2026-07-09","constituent_code":"039490","constituent_name":"키움증권","quantity":2.0,"valuation":669000.0,"weight":0.0685746664554362},{"snapshot_date":"2026-07-09","constituent_code":"011200","constituent_name":"HMM","quantity":32.0,"valuation":641600.0,"weight":0.06576607772467542},{"snapshot_date":"2026-07-09","constituent_code":"004170","constituent_name":"신세계","quantity":1.0,"valuation":625000.0,"weight":0.06406452396808314},{"snapshot_date":"2026-07-09","constituent_code":"006260","constituent_name":"LS","quantity":2.0,"valuation":617000.0,"weight":0.06324449806129168},{"snapshot_date":"2026-07-09","constituent_code":"005830","constituent_name":"DB손해보험","quantity":4.0,"valuation":605600.0,"weight":0.06207596114411384},{"snapshot_date":"2026-07-09","constituent_code":"024110","constituent_name":"기업은행","quantity":28.0,"valuation":586600.0,"weight":0.060128399615484114},{"snapshot_date":"2026-07-09","constituent_code":"161390","constituent_name":"한국타이어앤테크놀로지","quantity":8.0,"valuation":584000.0,"weight":0.05986189119577689},{"snapshot_date":"2026-07-09","constituent_code":"021240","constituent_name":"코웨이","quantity":6.0,"valuation":550200.0,"weight":0.05639728173958295},{"snapshot_date":"2026-07-09","constituent_code":"007660","constituent_name":"이수페타시스","quantity":6.0,"valuation":526800.0,"weight":0.05399870596221792},{"snapshot_date":"2026-07-09","constituent_code":"010950","constituent_name":"S-Oil","quantity":4.0,"valuation":526400.0,"weight":0.053957704666878346},{"snapshot_date":"2026-07-09","constituent_code":"272210","constituent_name":"한화시스템","quantity":8.0,"valuation":519200.0,"weight":0.053219681350766025},{"snapshot_date":"2026-07-09","constituent_code":"036570","constituent_name":"엔씨소프트/NC소프트","quantity":2.0,"valuation":517000.0,"weight":0.05299417422639837},{"snapshot_date":"2026-07-09","constituent_code":"138930","constituent_name":"BNK금융지주","quantity":28.0,"valuation":502040.0,"weight":0.05146072578069834},{"snapshot_date":"2026-07-09","constituent_code":"005940","constituent_name":"NH투자증권","quantity":15.0,"valuation":459750.0,"weight":0.04712586383092196},{"snapshot_date":"2026-07-09","constituent_code":"002380","constituent_name":"KCC","quantity":1.0,"valuation":447500.0,"weight":0.045870199161147526},{"snapshot_date":"2026-07-09","constituent_code":"307950","constituent_name":"현대오토에버","quantity":1.0,"valuation":441500.0,"weight":0.04525517973105393},{"snapshot_date":"2026-07-09","constituent_code":"003670","constituent_name":"포스코퓨처엠","quantity":3.0,"valuation":434100.0,"weight":0.044496655767271825},{"snapshot_date":"2026-07-09","constituent_code":"032640","constituent_name":"LG유플러스","quantity":29.0,"valuation":429490.0,"weight":0.044024115838483244},{"snapshot_date":"2026-07-09","constituent_code":"271560","constituent_name":"오리온","quantity":3.0,"valuation":420900.0,"weight":0.04314361302106591},{"snapshot_date":"2026-07-09","constituent_code":"009830","constituent_name":"한화솔루션","quantity":14.0,"valuation":417900.0,"weight":0.04283610330601911},{"snapshot_date":"2026-07-09","constituent_code":"175330","constituent_name":"JB금융지주","quantity":16.0,"valuation":416000.0,"weight":0.04264134715315614},{"snapshot_date":"2026-07-09","constituent_code":"000100","constituent_name":"유한양행","quantity":6.0,"valuation":414600.0,"weight":0.04249784261946763},{"snapshot_date":"2026-07-09","constituent_code":"128940","constituent_name":"한미약품","quantity":1.0,"valuation":409000.0,"weight":0.04192382448471361},{"snapshot_date":"2026-07-09","constituent_code":"443060","constituent_name":"HD현대마린솔루션","quantity":2.0,"valuation":395200.0,"weight":0.04050927979549833},{"snapshot_date":"2026-07-09","constituent_code":"078930","constituent_name":"GS","quantity":5.0,"valuation":393000.0,"weight":0.04028377267113068},{"snapshot_date":"2026-07-09","constituent_code":"0126Z0","constituent_name":"삼성에피스홀딩스","quantity":1.0,"valuation":380500.0,"weight":0.039002482191769015},{"snapshot_date":"2026-07-09","constituent_code":"267270","constituent_name":"HD건설기계","quantity":3.0,"valuation":375900.0,"weight":0.03853096729536393},{"snapshot_date":"2026-07-09","constituent_code":"090430","constituent_name":"아모레퍼시픽","quantity":3.0,"valuation":372900.0,"weight":0.03822345758031712},{"snapshot_date":"2026-07-09","constituent_code":"034220","constituent_name":"LG디스플레이","quantity":33.0,"valuation":370920.0,"weight":0.03802050116838624},{"snapshot_date":"2026-07-09","constituent_code":"001440","constituent_name":"대한전선","quantity":13.0,"valuation":366600.0,"weight":0.037577687178718844},{"snapshot_date":"2026-07-09","constituent_code":"010060","constituent_name":"OCI홀딩스","quantity":2.0,"valuation":361000.0,"weight":0.03700366904396482},{"snapshot_date":"2026-07-09","constituent_code":"062040","constituent_name":"산일전기","quantity":2.0,"valuation":356400.0,"weight":0.03653215414755973},{"snapshot_date":"2026-07-09","constituent_code":"064400","constituent_name":"LG씨앤에스/LGCNS","quantity":5.0,"valuation":356000.0,"weight":0.036491152852220154},{"snapshot_date":"2026-07-09","constituent_code":"000990","constituent_name":"DB하이텍","quantity":3.0,"valuation":335400.0,"weight":0.03437958614223214},{"snapshot_date":"2026-07-09","constituent_code":"326030","constituent_name":"SK바이오팜","quantity":4.0,"valuation":328400.0,"weight":0.033662063473789604},{"snapshot_date":"2026-07-09","constituent_code":"047040","constituent_name":"대우건설","quantity":20.0,"valuation":316600.0,"weight":0.032452525261272194},{"snapshot_date":"2026-07-09","constituent_code":"241560","constituent_name":"두산밥캣","quantity":5.0,"valuation":307000.0,"weight":0.03146849417312244},{"snapshot_date":"2026-07-09","constituent_code":"001040","constituent_name":"CJ","quantity":2.0,"valuation":284600.0,"weight":0.029172421634106337},{"snapshot_date":"2026-07-09","constituent_code":"000880","constituent_name":"한화","quantity":3.0,"valuation":280200.0,"weight":0.028721407385371035},{"snapshot_date":"2026-07-09","constituent_code":"066970","constituent_name":"엘앤에프","quantity":3.0,"valuation":275400.0,"weight":0.028229391841296154},{"snapshot_date":"2026-07-09","constituent_code":"082740","constituent_name":"한화엔진","quantity":6.0,"valuation":268500.0,"weight":0.027522119496688518},{"snapshot_date":"2026-07-09","constituent_code":"011790","constituent_name":"SKC","quantity":3.0,"valuation":266100.0,"weight":0.027276111724651077},{"snapshot_date":"2026-07-09","constituent_code":"111770","constituent_name":"영원무역","quantity":3.0,"valuation":256200.0,"weight":0.02626132966499664},{"snapshot_date":"2026-07-09","constituent_code":"051900","constituent_name":"LG생활건강","quantity":1.0,"valuation":256000.0,"weight":0.026240829017326855},{"snapshot_date":"2026-07-09","constituent_code":"139130","constituent_name":"iM금융지주","quantity":14.0,"valuation":253260.0,"weight":0.025959970144250777},{"snapshot_date":"2026-07-09","constituent_code":"047050","constituent_name":"포스코인터내셔널","quantity":5.0,"valuation":243750.0,"weight":0.024985164347552425},{"snapshot_date":"2026-07-09","constituent_code":"004020","constituent_name":"현대제철","quantity":9.0,"valuation":242100.0,"weight":0.024816034004276684},{"snapshot_date":"2026-07-09","constituent_code":"014680","constituent_name":"한솔케미칼","quantity":1.0,"valuation":238000.0,"weight":0.02439577072704606},{"snapshot_date":"2026-07-09","constituent_code":"001450","constituent_name":"현대해상","quantity":6.0,"valuation":227700.0,"weight":0.02333998737205205},{"snapshot_date":"2026-07-09","constituent_code":"011780","constituent_name":"금호석유화학","quantity":2.0,"valuation":225000.0,"weight":0.02306322862850993},{"snapshot_date":"2026-07-09","constituent_code":"161890","constituent_name":"한국콜마","quantity":2.0,"valuation":224200.0,"weight":0.022981226037830784},{"snapshot_date":"2026-07-09","constituent_code":"483650","constituent_name":"달바글로벌","quantity":1.0,"valuation":217500.0,"weight":0.022294454340892934},{"snapshot_date":"2026-07-09","constituent_code":"454910","constituent_name":"두산로보틱스","quantity":3.0,"valuation":217500.0,"weight":0.022294454340892934},{"snapshot_date":"2026-07-09","constituent_code":"012750","constituent_name":"에스원","quantity":3.0,"valuation":215400.0,"weight":0.022079197540360175},{"snapshot_date":"2026-07-09","constituent_code":"017800","constituent_name":"현대엘리베이터","quantity":3.0,"valuation":207900.0,"weight":0.021310423252743176},{"snapshot_date":"2026-07-09","constituent_code":"097950","constituent_name":"CJ제일제당","quantity":1.0,"valuation":198200.0,"weight":0.020316141840758525},{"snapshot_date":"2026-07-09","constituent_code":"052690","constituent_name":"한전기술","quantity":2.0,"valuation":189800.0,"weight":0.019455114638627487},{"snapshot_date":"2026-07-09","constituent_code":"009970","constituent_name":"영원무역홀딩스","quantity":1.0,"valuation":185200.0,"weight":0.018983599742222395},{"snapshot_date":"2026-07-09","constituent_code":"192820","constituent_name":"코스맥스","quantity":1.0,"valuation":179600.0,"weight":0.018409581607468372},{"snapshot_date":"2026-07-09","constituent_code":"375500","constituent_name":"DL이앤씨","quantity":3.0,"valuation":179100.0,"weight":0.018358329988293905},{"snapshot_date":"2026-07-09","constituent_code":"035250","constituent_name":"강원랜드","quantity":12.0,"valuation":177360.0,"weight":0.01817997435356676},{"snapshot_date":"2026-07-09","constituent_code":"009420","constituent_name":"한올바이오파마","quantity":3.0,"valuation":176100.0,"weight":0.018050820273247104},{"snapshot_date":"2026-07-09","constituent_code":"069960","constituent_name":"현대백화점","quantity":1.0,"valuation":168700.0,"weight":0.017292296309465},{"snapshot_date":"2026-07-09","constituent_code":"071970","constituent_name":"HD현대마린엔진","quantity":3.0,"valuation":167700.0,"weight":0.01718979307111607},{"snapshot_date":"2026-07-09","constituent_code":"139480","constituent_name":"이마트","quantity":2.0,"valuation":162200.0,"weight":0.016626025260196936},{"snapshot_date":"2026-07-09","constituent_code":"383220","constituent_name":"F&F","quantity":2.0,"valuation":160400.0,"weight":0.016441519431168856},{"snapshot_date":"2026-07-09","constituent_code":"023530","constituent_name":"롯데쇼핑","quantity":1.0,"valuation":159600.0,"weight":0.01635951684048971},{"snapshot_date":"2026-07-09","constituent_code":"008770","constituent_name":"호텔신라","quantity":3.0,"valuation":154500.0,"weight":0.01583675032491015},{"snapshot_date":"2026-07-09","constituent_code":"377300","constituent_name":"카카오페이","quantity":4.0,"valuation":152600.0,"weight":0.015641994172047178},{"snapshot_date":"2026-07-09","constituent_code":"030000","constituent_name":"제일기획","quantity":8.0,"valuation":151840.0,"weight":0.01556409171090199},{"snapshot_date":"2026-07-09","constituent_code":"088350","constituent_name":"한화생명","quantity":35.0,"valuation":151725.0,"weight":0.015552303838491863},{"snapshot_date":"2026-07-09","constituent_code":"029780","constituent_name":"삼성카드","quantity":3.0,"valuation":146550.0,"weight":0.015021849580036134},{"snapshot_date":"2026-07-09","constituent_code":"204320","constituent_name":"HL만도","quantity":3.0,"valuation":146100.0,"weight":0.014975723122779115},{"snapshot_date":"2026-07-09","constituent_code":"081660","constituent_name":"미스토홀딩스","quantity":3.0,"valuation":143550.0,"weight":0.014714339864989335},{"snapshot_date":"2026-07-09","constituent_code":"450080","constituent_name":"에코프로머티","quantity":4.0,"valuation":143400.0,"weight":0.014698964379236996},{"snapshot_date":"2026-07-09","constituent_code":"069620","constituent_name":"대웅제약","quantity":1.0,"valuation":134900.0,"weight":0.013827686853271065},{"snapshot_date":"2026-07-09","constituent_code":"036460","constituent_name":"한국가스공사","quantity":4.0,"valuation":132800.0,"weight":0.013612430052738305},{"snapshot_date":"2026-07-09","constituent_code":"018880","constituent_name":"한온시스템","quantity":37.0,"valuation":132275.0,"weight":0.013558615852605116},{"snapshot_date":"2026-07-09","constituent_code":"051600","constituent_name":"한전KPS","quantity":3.0,"valuation":131700.0,"weight":0.01349967649055448},{"snapshot_date":"2026-07-09","constituent_code":"282330","constituent_name":"BGF리테일","quantity":1.0,"valuation":125400.0,"weight":0.012853906088956202},{"snapshot_date":"2026-07-09","constituent_code":"103140","constituent_name":"풍산","quantity":2.0,"valuation":125000.0,"weight":0.012812904793616627},{"snapshot_date":"2026-07-09","constituent_code":"028670","constituent_name":"팬오션","quantity":24.0,"valuation":124080.0,"weight":0.012718601814335609},{"snapshot_date":"2026-07-09","constituent_code":"011170","constituent_name":"롯데케미칼","quantity":2.0,"valuation":121400.0,"weight":0.012443893135560468},{"snapshot_date":"2026-07-09","constituent_code":"006280","constituent_name":"녹십자","quantity":1.0,"valuation":121200.0,"weight":0.012423392487890683},{"snapshot_date":"2026-07-09","constituent_code":"011210","constituent_name":"현대위아","quantity":2.0,"valuation":121200.0,"weight":0.012423392487890683},{"snapshot_date":"2026-07-09","constituent_code":"457190","constituent_name":"이수스페셜티케미컬","quantity":2.0,"valuation":120400.0,"weight":0.012341389897211535},{"snapshot_date":"2026-07-09","constituent_code":"112610","constituent_name":"씨에스윈드","quantity":3.0,"valuation":117150.0,"weight":0.012008254372577503},{"snapshot_date":"2026-07-09","constituent_code":"251270","constituent_name":"넷마블","quantity":3.0,"valuation":116400.0,"weight":0.011931376943815804},{"snapshot_date":"2026-07-09","constituent_code":"005850","constituent_name":"에스엘","quantity":2.0,"valuation":114800.0,"weight":0.01176737176245751},{"snapshot_date":"2026-07-09","constituent_code":"302440","constituent_name":"SK바이오사이언스","quantity":3.0,"valuation":113850.0,"weight":0.011669993686026024},{"snapshot_date":"2026-07-09","constituent_code":"120110","constituent_name":"코오롱인더","quantity":2.0,"valuation":112200.0,"weight":0.011500863342750285},{"snapshot_date":"2026-07-09","constituent_code":"007340","constituent_name":"DN오토모티브","quantity":3.0,"valuation":106200.0,"weight":0.010885843912656687},{"snapshot_date":"2026-07-09","constituent_code":"008930","constituent_name":"한미사이언스","quantity":3.0,"valuation":100950.0,"weight":0.010347701911324789},{"snapshot_date":"2026-07-09","constituent_code":"022100","constituent_name":"포스코DX","quantity":5.0,"valuation":96200.0,"weight":0.009860811529167356},{"snapshot_date":"2026-07-09","constituent_code":"004000","constituent_name":"롯데정밀화학","quantity":2.0,"valuation":86700.0,"weight":0.008887030764852493},{"snapshot_date":"2026-07-09","constituent_code":"456040","constituent_name":"OCI","quantity":1.0,"valuation":83700.0,"weight":0.008579521049805694},{"snapshot_date":"2026-07-09","constituent_code":"001800","constituent_name":"오리온홀딩스","quantity":3.0,"valuation":78150.0,"weight":0.008010628076969116},{"snapshot_date":"2026-07-09","constituent_code":"073240","constituent_name":"금호타이어","quantity":12.0,"valuation":76800.0,"weight":0.007872248705198056},{"snapshot_date":"2026-07-09","constituent_code":"000240","constituent_name":"한국앤컴퍼니","quantity":3.0,"valuation":76800.0,"weight":0.007872248705198056},{"snapshot_date":"2026-07-09","constituent_code":"026960","constituent_name":"동서","quantity":3.0,"valuation":76500.0,"weight":0.007841497733693376},{"snapshot_date":"2026-07-09","constituent_code":"007070","constituent_name":"GS리테일","quantity":3.0,"valuation":75150.0,"weight":0.007703118361922317},{"snapshot_date":"2026-07-09","constituent_code":"002790","constituent_name":"아모레퍼시픽홀딩스","quantity":3.0,"valuation":74400.0,"weight":0.007626240933160617},{"snapshot_date":"2026-07-09","constituent_code":"000120","constituent_name":"CJ대한통운","quantity":1.0,"valuation":74300.0,"weight":0.007615990609325724},{"snapshot_date":"2026-07-09","constituent_code":"004990","constituent_name":"롯데지주","quantity":3.0,"valuation":72000.0,"weight":0.007380233161123178},{"snapshot_date":"2026-07-09","constituent_code":"017960","constituent_name":"한국카본","quantity":3.0,"valuation":72000.0,"weight":0.007380233161123178},{"snapshot_date":"2026-07-09","constituent_code":"185750","constituent_name":"종근당","quantity":1.0,"valuation":69600.0,"weight":0.007134225389085739},{"snapshot_date":"2026-07-09","constituent_code":"192080","constituent_name":"더블유게임즈","quantity":1.0,"valuation":64500.0,"weight":0.00661145887350618},{"snapshot_date":"2026-07-09","constituent_code":"093370","constituent_name":"후성","quantity":6.0,"valuation":64440.0,"weight":0.006605308679205244},{"snapshot_date":"2026-07-09","constituent_code":"001430","constituent_name":"세아베스틸지주","quantity":2.0,"valuation":60300.0,"weight":0.006180945272440661},{"snapshot_date":"2026-07-09","constituent_code":"361610","constituent_name":"SK아이이테크놀로지","quantity":4.0,"valuation":57600.0,"weight":0.005904186528898542},{"snapshot_date":"2026-07-09","constituent_code":"034230","constituent_name":"파라다이스","quantity":4.0,"valuation":51680.0,"weight":0.005297367357872859},{"snapshot_date":"2026-07-09","constituent_code":"069260","constituent_name":"TKG휴켐스","quantity":3.0,"valuation":46860.0,"weight":0.0048033017490310016},{"snapshot_date":"2026-07-09","constituent_code":"000080","constituent_name":"하이트진로","quantity":3.0,"valuation":45450.0,"weight":0.004658772182959006},{"snapshot_date":"2026-07-09","constituent_code":"000210","constituent_name":"DL","quantity":1.0,"valuation":44300.0,"weight":0.004540893458857733},{"snapshot_date":"2026-07-09","constituent_code":"300720","constituent_name":"한일시멘트","quantity":3.0,"valuation":43410.0,"weight":0.004449665576727183},{"snapshot_date":"2026-07-09","constituent_code":"285130","constituent_name":"SK케미칼","quantity":1.0,"valuation":40600.0,"weight":0.00416163147696668},{"snapshot_date":"2026-07-09","constituent_code":"000670","constituent_name":"영풍","quantity":1.0,"valuation":36650.0,"weight":0.0037567436854883955},{"snapshot_date":"2026-07-09","constituent_code":"003090","constituent_name":"대웅","quantity":2.0,"valuation":35640.0,"weight":0.003653215414755973},{"snapshot_date":"2026-07-09","constituent_code":"001680","constituent_name":"대상","quantity":2.0,"valuation":35100.0,"weight":0.0035978636660475493},{"snapshot_date":"2026-07-09","constituent_code":"006040","constituent_name":"동원산업","quantity":1.0,"valuation":35100.0,"weight":0.0035978636660475493},{"snapshot_date":"2026-07-09","constituent_code":"009240","constituent_name":"한샘","quantity":1.0,"valuation":34300.0,"weight":0.003515861075368403},{"snapshot_date":"2026-07-09","constituent_code":"005420","constituent_name":"코스모화학","quantity":3.0,"valuation":27780.0,"weight":0.0028475399613333593},{"snapshot_date":"2026-07-09","constituent_code":"137310","constituent_name":"에스디바이오센서","quantity":3.0,"valuation":19290.0,"weight":0.001977287467750918},{"snapshot_date":"2026-07-09","constituent_code":"014820","constituent_name":"동원시스템즈","quantity":1.0,"valuation":18920.0,"weight":0.0019393612695618129},{"snapshot_date":"2026-07-09","constituent_code":"008730","constituent_name":"율촌화학","quantity":1.0,"valuation":13950.0,"weight":0.0014299201749676156}],"top_changes":{"additions":[],"removals":[],"weight_changes":[{"snapshot_date":"2026-07-09","previous_snapshot_date":"2026-07-08","change_type":"비중축소","constituent_code":"005930","constituent_name":"삼성전자","previous_weight":14.303153210129576,"weight":13.795654591287024,"weight_delta":-0.5074986188425523,"active_signal_ratio":1.0,"active_change_type":"drift"},{"snapshot_date":"2026-07-09","previous_snapshot_date":"2026-07-08","change_type":"비중축소","constituent_code":"000660","constituent_name":"SK하이닉스","previous_weight":12.718806997065487,"weight":12.342209923118327,"weight_delta":-0.3765970739471598,"active_signal_ratio":1.0,"active_change_type":"drift"},{"snapshot_date":"2026-07-09","previous_snapshot_date":"2026-07-08","change_type":"비중축소","constituent_code":"009150","constituent_name":"삼성전기","previous_weight":0.9851600650721736,"weight":0.9096137371084316,"weight_delta":-0.07554632796374194,"active_signal_ratio":1.0,"active_change_type":"drift"}]}},"2026-07-10":{"ticker":"0192S0","snapshot_date":"2026-07-10","kpis":{"snapshot_date":"2026-07-10","holding_count":186,"total_valuation":412710895.0,"total_weight":42.12259076419328,"top_holding":{"etf_idx":"K55210EU9643","ticker":"0192S0","etf_name":"SOL 코스피200채권혼합50","source_url":"https://www.funetf.co.kr/product/etf/view/KR70192S0000","snapshot_date":"2026-07-10","constituent_code":"005930","constituent_name":"삼성전자","quantity":485.0,"valuation":134830000.0,"weight":13.761179996801829}},"holdings":[{"snapshot_date":"2026-07-10","constituent_code":"005930","constituent_name":"삼성전자","quantity":485.0,"valuation":134830000.0,"weight":13.761179996801829},{"snapshot_date":"2026-07-10","constituent_code":"000660","constituent_name":"SK하이닉스","quantity":58.0,"valuation":126788000.0,"weight":12.940387817507307},{"snapshot_date":"2026-07-10","constituent_code":"402340","constituent_name":"SK스퀘어","quantity":9.0,"valuation":11943000.0,"weight":1.2189406860624805},{"snapshot_date":"2026-07-10","constituent_code":"009150","constituent_name":"삼성전기","quantity":6.0,"valuation":8958000.0,"weight":0.9142820619398561},{"snapshot_date":"2026-07-10","constituent_code":"005380","constituent_name":"현대차","quantity":14.0,"valuation":6237000.0,"weight":0.6365681201516948},{"snapshot_date":"2026-07-10","constituent_code":"105560","constituent_name":"KB금융","quantity":31.0,"valuation":5313400.0,"weight":0.5423025572573377},{"snapshot_date":"2026-07-10","constituent_code":"055550","constituent_name":"신한지주","quantity":43.0,"valuation":4515000.0,"weight":0.46081530583371844},{"snapshot_date":"2026-07-10","constituent_code":"028260","constituent_name":"삼성물산","quantity":10.0,"valuation":3785000.0,"weight":0.3863091766513011},{"snapshot_date":"2026-07-10","constituent_code":"000270","constituent_name":"기아","quantity":26.0,"valuation":3764800.0,"weight":0.384247500199952},{"snapshot_date":"2026-07-10","constituent_code":"034020","constituent_name":"두산에너빌리티","quantity":45.0,"valuation":3294000.0,"weight":0.33619615003682585},{"snapshot_date":"2026-07-10","constituent_code":"012330","constituent_name":"현대모비스","quantity":7.0,"valuation":3255000.0,"weight":0.33221568560105286},{"snapshot_date":"2026-07-10","constituent_code":"086790","constituent_name":"하나금융지주","quantity":26.0,"valuation":3187600.0,"weight":0.3253366265505118},{"snapshot_date":"2026-07-10","constituent_code":"032830","constituent_name":"삼성생명","quantity":9.0,"valuation":2934000.0,"weight":0.29945340139892135},{"snapshot_date":"2026-07-10","constituent_code":"012450","constituent_name":"한화에어로스페이스","quantity":3.0,"valuation":2859000.0,"weight":0.29179866209935795},{"snapshot_date":"2026-07-10","constituent_code":"298040","constituent_name":"효성중공업","quantity":1.0,"valuation":2770000.0,"weight":0.28271503813054266},{"snapshot_date":"2026-07-10","constituent_code":"068270","constituent_name":"셀트리온","quantity":16.0,"valuation":2769600.0,"weight":0.28267421285427835},{"snapshot_date":"2026-07-10","constituent_code":"035420","constituent_name":"네이버/NAVER","quantity":14.0,"valuation":2581600.0,"weight":0.2634863330100393},{"snapshot_date":"2026-07-10","constituent_code":"267260","constituent_name":"HD현대일렉트릭","quantity":3.0,"valuation":2445000.0,"weight":0.24954450116576782},{"snapshot_date":"2026-07-10","constituent_code":"006400","constituent_name":"삼성SDI","quantity":6.0,"valuation":2409000.0,"weight":0.24587022630197736},{"snapshot_date":"2026-07-10","constituent_code":"316140","constituent_name":"우리금융지주","quantity":70.0,"valuation":2103500.0,"weight":0.21468992155508898},{"snapshot_date":"2026-07-10","constituent_code":"005490","constituent_name":"POSCO홀딩스/포스코홀딩스","quantity":7.0,"valuation":2079000.0,"weight":0.21218937338389826},{"snapshot_date":"2026-07-10","constituent_code":"066570","constituent_name":"LG전자","quantity":11.0,"valuation":1958000.0,"weight":0.19983972731393593},{"snapshot_date":"2026-07-10","constituent_code":"000810","constituent_name":"삼성화재","quantity":3.0,"valuation":1866000.0,"weight":0.19044991377313814},{"snapshot_date":"2026-07-10","constituent_code":"034730","constituent_name":"SK","quantity":3.0,"valuation":1830000.0,"weight":0.18677563890934767},{"snapshot_date":"2026-07-10","constituent_code":"010120","constituent_name":"LS ELECTRIC","quantity":9.0,"valuation":1704600.0,"weight":0.17397691480047764},{"snapshot_date":"2026-07-10","constituent_code":"009540","constituent_name":"HD한국조선해양","quantity":5.0,"valuation":1637500.0,"weight":0.16712847470713488},{"snapshot_date":"2026-07-10","constituent_code":"033780","constituent_name":"KT&G","quantity":9.0,"valuation":1587600.0,"weight":0.16203552149315867},{"snapshot_date":"2026-07-10","constituent_code":"373220","constituent_name":"LG에너지솔루션","quantity":5.0,"valuation":1567500.0,"weight":0.15998405136087568},{"snapshot_date":"2026-07-10","constituent_code":"329180","constituent_name":"HD현대중공업","quantity":3.0,"valuation":1521000.0,"weight":0.15523811299514637},{"snapshot_date":"2026-07-10","constituent_code":"011070","constituent_name":"LG이노텍","quantity":2.0,"valuation":1482000.0,"weight":0.15125764855937338},{"snapshot_date":"2026-07-10","constituent_code":"010140","constituent_name":"삼성중공업","quantity":69.0,"valuation":1445550.0,"weight":0.14753744525978554},{"snapshot_date":"2026-07-10","constituent_code":"079550","constituent_name":"LIG디펜스앤에어로스페이스","quantity":2.0,"valuation":1388000.0,"weight":0.14166370863725386},{"snapshot_date":"2026-07-10","constituent_code":"030200","constituent_name":"KT","quantity":23.0,"valuation":1334000.0,"weight":0.1361522963415682},{"snapshot_date":"2026-07-10","constituent_code":"207940","constituent_name":"삼성바이오로직스","quantity":1.0,"valuation":1325000.0,"weight":0.13523372762562058},{"snapshot_date":"2026-07-10","constituent_code":"017670","constituent_name":"SK텔레콤","quantity":15.0,"valuation":1300500.0,"weight":0.13273317945442986},{"snapshot_date":"2026-07-10","constituent_code":"064350","constituent_name":"현대로템","quantity":8.0,"valuation":1284800.0,"weight":0.1311307873610546},{"snapshot_date":"2026-07-10","constituent_code":"051910","constituent_name":"LG화학","quantity":5.0,"valuation":1257500.0,"weight":0.1283444622560135},{"snapshot_date":"2026-07-10","constituent_code":"000150","constituent_name":"두산","quantity":1.0,"valuation":1203000.0,"weight":0.12278201836499741},{"snapshot_date":"2026-07-10","constituent_code":"047810","constituent_name":"한국항공우주","quantity":8.0,"valuation":1200000.0,"weight":0.12247582879301487},{"snapshot_date":"2026-07-10","constituent_code":"035720","constituent_name":"카카오","quantity":35.0,"valuation":1177750.0,"weight":0.12020492280081106},{"snapshot_date":"2026-07-10","constituent_code":"015760","constituent_name":"한국전력","quantity":33.0,"valuation":1161600.0,"weight":0.1185566022716384},{"snapshot_date":"2026-07-10","constituent_code":"006800","constituent_name":"미래에셋증권","quantity":28.0,"valuation":1127000.0,"weight":0.11502521587477313},{"snapshot_date":"2026-07-10","constituent_code":"042660","constituent_name":"한화오션","quantity":14.0,"valuation":1100400.0,"weight":0.11231033500319464},{"snapshot_date":"2026-07-10","constituent_code":"278470","constituent_name":"에이피알","quantity":3.0,"valuation":1096500.0,"weight":0.11191228855961734},{"snapshot_date":"2026-07-10","constituent_code":"010130","constituent_name":"고려아연","quantity":1.0,"valuation":1003000.0,"weight":0.10236938023282827},{"snapshot_date":"2026-07-10","constituent_code":"267250","constituent_name":"HD현대","quantity":5.0,"valuation":947000.0,"weight":0.09665384155582091},{"snapshot_date":"2026-07-10","constituent_code":"003550","constituent_name":"LG","quantity":9.0,"valuation":911700.0,"weight":0.09305101092549305},{"snapshot_date":"2026-07-10","constituent_code":"138040","constituent_name":"메리츠금융지주","quantity":8.0,"valuation":903200.0,"weight":0.09218347380487586},{"snapshot_date":"2026-07-10","constituent_code":"071050","constituent_name":"한국금융지주","quantity":4.0,"valuation":890000.0,"weight":0.0908362396881527},{"snapshot_date":"2026-07-10","constituent_code":"042700","constituent_name":"한미반도체","quantity":4.0,"valuation":862000.0,"weight":0.08797847034964902},{"snapshot_date":"2026-07-10","constituent_code":"096770","constituent_name":"SK이노베이션","quantity":8.0,"valuation":792000.0,"weight":0.08083404700338982},{"snapshot_date":"2026-07-10","constituent_code":"000720","constituent_name":"현대건설","quantity":8.0,"valuation":791200.0,"weight":0.08075239645086114},{"snapshot_date":"2026-07-10","constituent_code":"323410","constituent_name":"카카오뱅크","quantity":36.0,"valuation":777600.0,"weight":0.07936433705787364},{"snapshot_date":"2026-07-10","constituent_code":"018260","constituent_name":"삼성에스디에스","quantity":4.0,"valuation":753200.0,"weight":0.076873995205749},{"snapshot_date":"2026-07-10","constituent_code":"086280","constituent_name":"현대글로비스","quantity":4.0,"valuation":737200.0,"weight":0.07524098415517547},{"snapshot_date":"2026-07-10","constituent_code":"259960","constituent_name":"크래프톤","quantity":3.0,"valuation":715500.0,"weight":0.07302621291783512},{"snapshot_date":"2026-07-10","constituent_code":"003490","constituent_name":"대한항공","quantity":26.0,"valuation":694200.0,"weight":0.0708522669567591},{"snapshot_date":"2026-07-10","constituent_code":"028050","constituent_name":"삼성E&A","quantity":16.0,"valuation":672800.0,"weight":0.068668114676617},{"snapshot_date":"2026-07-10","constituent_code":"352820","constituent_name":"하이브","quantity":3.0,"valuation":648000.0,"weight":0.06613694754822803},{"snapshot_date":"2026-07-10","constituent_code":"016360","constituent_name":"삼성증권","quantity":6.0,"valuation":639600.0,"weight":0.06527961674667693},{"snapshot_date":"2026-07-10","constituent_code":"039490","constituent_name":"키움증권","quantity":2.0,"valuation":630000.0,"weight":0.0642998101163328},{"snapshot_date":"2026-07-10","constituent_code":"180640","constituent_name":"한진칼","quantity":5.0,"valuation":630000.0,"weight":0.0642998101163328},{"snapshot_date":"2026-07-10","constituent_code":"006260","constituent_name":"LS","quantity":2.0,"valuation":627000.0,"weight":0.06399362054435027},{"snapshot_date":"2026-07-10","constituent_code":"011200","constituent_name":"HMM","quantity":32.0,"valuation":618240.0,"weight":0.06309954699416126},{"snapshot_date":"2026-07-10","constituent_code":"004170","constituent_name":"신세계","quantity":1.0,"valuation":606000.0,"weight":0.061850293540472515},{"snapshot_date":"2026-07-10","constituent_code":"005830","constituent_name":"DB손해보험","quantity":4.0,"valuation":586000.0,"weight":0.059809029727255596},{"snapshot_date":"2026-07-10","constituent_code":"024110","constituent_name":"기업은행","quantity":28.0,"valuation":574000.0,"weight":0.05858427143932545},{"snapshot_date":"2026-07-10","constituent_code":"161390","constituent_name":"한국타이어앤테크놀로지","quantity":8.0,"valuation":565600.0,"weight":0.057726940637774345},{"snapshot_date":"2026-07-10","constituent_code":"007660","constituent_name":"이수페타시스","quantity":6.0,"valuation":550800.0,"weight":0.05621640541599383},{"snapshot_date":"2026-07-10","constituent_code":"010950","constituent_name":"S-Oil","quantity":4.0,"valuation":534000.0,"weight":0.05450174381289162},{"snapshot_date":"2026-07-10","constituent_code":"272210","constituent_name":"한화시스템","quantity":8.0,"valuation":517600.0,"weight":0.052827907486053746},{"snapshot_date":"2026-07-10","constituent_code":"021240","constituent_name":"코웨이","quantity":6.0,"valuation":510000.0,"weight":0.052052227237031325},{"snapshot_date":"2026-07-10","constituent_code":"036570","constituent_name":"엔씨소프트/NC소프트","quantity":2.0,"valuation":499000.0,"weight":0.05092953213976202},{"snapshot_date":"2026-07-10","constituent_code":"138930","constituent_name":"BNK금융지주","quantity":28.0,"valuation":482160.0,"weight":0.04921078800903338},{"snapshot_date":"2026-07-10","constituent_code":"002380","constituent_name":"KCC","quantity":1.0,"valuation":444500.0,"weight":0.045367088248745926},{"snapshot_date":"2026-07-10","constituent_code":"032640","constituent_name":"LG유플러스","quantity":29.0,"valuation":440800.0,"weight":0.0449894544433008},{"snapshot_date":"2026-07-10","constituent_code":"005940","constituent_name":"NH투자증권","quantity":15.0,"valuation":438750.0,"weight":0.04478022490244606},{"snapshot_date":"2026-07-10","constituent_code":"003670","constituent_name":"포스코퓨처엠","quantity":3.0,"valuation":438000.0,"weight":0.04470367750945043},{"snapshot_date":"2026-07-10","constituent_code":"307950","constituent_name":"현대오토에버","quantity":1.0,"valuation":433000.0,"weight":0.0441933615561462},{"snapshot_date":"2026-07-10","constituent_code":"009830","constituent_name":"한화솔루션","quantity":14.0,"valuation":431200.0,"weight":0.04400964781295668},{"snapshot_date":"2026-07-10","constituent_code":"271560","constituent_name":"오리온","quantity":3.0,"valuation":406500.0,"weight":0.04148868700363379},{"snapshot_date":"2026-07-10","constituent_code":"000100","constituent_name":"유한양행","quantity":6.0,"valuation":404400.0,"weight":0.04127435430324601},{"snapshot_date":"2026-07-10","constituent_code":"128940","constituent_name":"한미약품","quantity":1.0,"valuation":401000.0,"weight":0.040927339454999136},{"snapshot_date":"2026-07-10","constituent_code":"175330","constituent_name":"JB금융지주","quantity":16.0,"valuation":398400.0,"weight":0.04066197515928094},{"snapshot_date":"2026-07-10","constituent_code":"443060","constituent_name":"HD현대마린솔루션","quantity":2.0,"valuation":378600.0,"weight":0.03864112398419619},{"snapshot_date":"2026-07-10","constituent_code":"078930","constituent_name":"GS","quantity":5.0,"valuation":378000.0,"weight":0.03857988606979969},{"snapshot_date":"2026-07-10","constituent_code":"0126Z0","constituent_name":"삼성에피스홀딩스","quantity":1.0,"valuation":368500.0,"weight":0.03761028575852165},{"snapshot_date":"2026-07-10","constituent_code":"010060","constituent_name":"OCI홀딩스","quantity":2.0,"valuation":366400.0,"weight":0.037395953058133875},{"snapshot_date":"2026-07-10","constituent_code":"267270","constituent_name":"HD건설기계","quantity":3.0,"valuation":363600.0,"weight":0.03711017612428351},{"snapshot_date":"2026-07-10","constituent_code":"001440","constituent_name":"대한전선","quantity":13.0,"valuation":361400.0,"weight":0.036885637104829644},{"snapshot_date":"2026-07-10","constituent_code":"062040","constituent_name":"산일전기","quantity":2.0,"valuation":359200.0,"weight":0.036661098085375786},{"snapshot_date":"2026-07-10","constituent_code":"034220","constituent_name":"LG디스플레이","quantity":33.0,"valuation":352440.0,"weight":0.03597115091650847},{"snapshot_date":"2026-07-10","constituent_code":"000990","constituent_name":"DB하이텍","quantity":3.0,"valuation":350100.0,"weight":0.03573232305036209},{"snapshot_date":"2026-07-10","constituent_code":"090430","constituent_name":"아모레퍼시픽","quantity":3.0,"valuation":348900.0,"weight":0.035609847221569076},{"snapshot_date":"2026-07-10","constituent_code":"064400","constituent_name":"LG씨앤에스/LGCNS","quantity":5.0,"valuation":345500.0,"weight":0.0352628323733222},{"snapshot_date":"2026-07-10","constituent_code":"326030","constituent_name":"SK바이오팜","quantity":4.0,"valuation":320800.0,"weight":0.03274187156399931},{"snapshot_date":"2026-07-10","constituent_code":"047040","constituent_name":"대우건설","quantity":20.0,"valuation":320800.0,"weight":0.03274187156399931},{"snapshot_date":"2026-07-10","constituent_code":"241560","constituent_name":"두산밥캣","quantity":5.0,"valuation":300500.0,"weight":0.03066998879358414},{"snapshot_date":"2026-07-10","constituent_code":"011790","constituent_name":"SKC","quantity":3.0,"valuation":275700.0,"weight":0.028138821665195168},{"snapshot_date":"2026-07-10","constituent_code":"000880","constituent_name":"한화","quantity":3.0,"valuation":274800.0,"weight":0.028046964793600405},{"snapshot_date":"2026-07-10","constituent_code":"066970","constituent_name":"엘앤에프","quantity":3.0,"valuation":274500.0,"weight":0.028016345836402154},{"snapshot_date":"2026-07-10","constituent_code":"001040","constituent_name":"CJ","quantity":2.0,"valuation":274200.0,"weight":0.0279857268792039},{"snapshot_date":"2026-07-10","constituent_code":"082740","constituent_name":"한화엔진","quantity":6.0,"valuation":255600.0,"weight":0.026087351532912167},{"snapshot_date":"2026-07-10","constituent_code":"111770","constituent_name":"영원무역","quantity":3.0,"valuation":247200.0,"weight":0.025230020731361064},{"snapshot_date":"2026-07-10","constituent_code":"012750","constituent_name":"에스원","quantity":3.0,"valuation":246000.0,"weight":0.02510754490256805},{"snapshot_date":"2026-07-10","constituent_code":"047050","constituent_name":"포스코인터내셔널","quantity":5.0,"valuation":243500.0,"weight":0.024852386925915935},{"snapshot_date":"2026-07-10","constituent_code":"014680","constituent_name":"한솔케미칼","quantity":1.0,"valuation":243000.0,"weight":0.02480135533058551},{"snapshot_date":"2026-07-10","constituent_code":"139130","constituent_name":"iM금융지주","quantity":14.0,"valuation":242340.0,"weight":0.024733993624749352},{"snapshot_date":"2026-07-10","constituent_code":"051900","constituent_name":"LG생활건강","quantity":1.0,"valuation":241000.0,"weight":0.02459722894926382},{"snapshot_date":"2026-07-10","constituent_code":"004020","constituent_name":"현대제철","quantity":9.0,"valuation":234000.0,"weight":0.0238827866146379},{"snapshot_date":"2026-07-10","constituent_code":"011780","constituent_name":"금호석유화학","quantity":2.0,"valuation":223800.0,"weight":0.022841742069897274},{"snapshot_date":"2026-07-10","constituent_code":"001450","constituent_name":"현대해상","quantity":6.0,"valuation":216300.0,"weight":0.02207626813994093},{"snapshot_date":"2026-07-10","constituent_code":"454910","constituent_name":"두산로보틱스","quantity":3.0,"valuation":211200.0,"weight":0.021555745867570617},{"snapshot_date":"2026-07-10","constituent_code":"161890","constituent_name":"한국콜마","quantity":2.0,"valuation":205600.0,"weight":0.02098419199986988},{"snapshot_date":"2026-07-10","constituent_code":"017800","constituent_name":"현대엘리베이터","quantity":3.0,"valuation":204600.0,"weight":0.020882128809209036},{"snapshot_date":"2026-07-10","constituent_code":"483650","constituent_name":"달바글로벌","quantity":1.0,"valuation":199900.0,"weight":0.020402431813103063},{"snapshot_date":"2026-07-10","constituent_code":"052690","constituent_name":"한전기술","quantity":2.0,"valuation":191800.0,"weight":0.01957571996875021},{"snapshot_date":"2026-07-10","constituent_code":"097950","constituent_name":"CJ제일제당","quantity":1.0,"valuation":191200.0,"weight":0.019514482054353702},{"snapshot_date":"2026-07-10","constituent_code":"009970","constituent_name":"영원무역홀딩스","quantity":1.0,"valuation":188000.0,"weight":0.019187879844238996},{"snapshot_date":"2026-07-10","constituent_code":"375500","constituent_name":"DL이앤씨","quantity":3.0,"valuation":185700.0,"weight":0.018953134505719053},{"snapshot_date":"2026-07-10","constituent_code":"035250","constituent_name":"강원랜드","quantity":12.0,"valuation":176520.0,"weight":0.018016194415452488},{"snapshot_date":"2026-07-10","constituent_code":"192820","constituent_name":"코스맥스","quantity":1.0,"valuation":173500.0,"weight":0.017707963579656733},{"snapshot_date":"2026-07-10","constituent_code":"069960","constituent_name":"현대백화점","quantity":1.0,"valuation":167600.0,"weight":0.017105790754757745},{"snapshot_date":"2026-07-10","constituent_code":"009420","constituent_name":"한올바이오파마","quantity":3.0,"valuation":166800.0,"weight":0.017024140202229067},{"snapshot_date":"2026-07-10","constituent_code":"071970","constituent_name":"HD현대마린엔진","quantity":3.0,"valuation":163500.0,"weight":0.016687331673048277},{"snapshot_date":"2026-07-10","constituent_code":"030000","constituent_name":"제일기획","quantity":8.0,"valuation":159920.0,"weight":0.016321945450482447},{"snapshot_date":"2026-07-10","constituent_code":"139480","constituent_name":"이마트","quantity":2.0,"valuation":159200.0,"weight":0.01624845995320664},{"snapshot_date":"2026-07-10","constituent_code":"023530","constituent_name":"롯데쇼핑","quantity":1.0,"valuation":158400.0,"weight":0.016166809400677964},{"snapshot_date":"2026-07-10","constituent_code":"081660","constituent_name":"미스토홀딩스","quantity":3.0,"valuation":157200.0,"weight":0.01604433357188495},{"snapshot_date":"2026-07-10","constituent_code":"383220","constituent_name":"F&F","quantity":2.0,"valuation":157000.0,"weight":0.01602392093375278},{"snapshot_date":"2026-07-10","constituent_code":"029780","constituent_name":"삼성카드","quantity":3.0,"valuation":155100.0,"weight":0.015830000871497173},{"snapshot_date":"2026-07-10","constituent_code":"377300","constituent_name":"카카오페이","quantity":4.0,"valuation":149800.0,"weight":0.01528906596099469},{"snapshot_date":"2026-07-10","constituent_code":"088350","constituent_name":"한화생명","quantity":35.0,"valuation":148575.0,"weight":0.015164038552435154},{"snapshot_date":"2026-07-10","constituent_code":"008770","constituent_name":"호텔신라","quantity":3.0,"valuation":147150.0,"weight":0.015018598505743448},{"snapshot_date":"2026-07-10","constituent_code":"204320","constituent_name":"HL만도","quantity":3.0,"valuation":145050.0,"weight":0.014804265805355673},{"snapshot_date":"2026-07-10","constituent_code":"450080","constituent_name":"에코프로머티","quantity":4.0,"valuation":142000.0,"weight":0.014492973073840093},{"snapshot_date":"2026-07-10","constituent_code":"051600","constituent_name":"한전KPS","quantity":3.0,"valuation":134250.0,"weight":0.013701983346218539},{"snapshot_date":"2026-07-10","constituent_code":"018880","constituent_name":"한온시스템","quantity":37.0,"valuation":132090.0,"weight":0.013481526854391112},{"snapshot_date":"2026-07-10","constituent_code":"069620","constituent_name":"대웅제약","quantity":1.0,"valuation":131600.0,"weight":0.013431515890967298},{"snapshot_date":"2026-07-10","constituent_code":"036460","constituent_name":"한국가스공사","quantity":4.0,"valuation":129200.0,"weight":0.013186564233381269},{"snapshot_date":"2026-07-10","constituent_code":"103140","constituent_name":"풍산","quantity":2.0,"valuation":123000.0,"weight":0.012553772451284025},{"snapshot_date":"2026-07-10","constituent_code":"011170","constituent_name":"롯데케미칼","quantity":2.0,"valuation":122600.0,"weight":0.012512947175019686},{"snapshot_date":"2026-07-10","constituent_code":"006280","constituent_name":"녹십자","quantity":1.0,"valuation":120600.0,"weight":0.012308820793697994},{"snapshot_date":"2026-07-10","constituent_code":"282330","constituent_name":"BGF리테일","quantity":1.0,"valuation":120200.0,"weight":0.012267995517433657},{"snapshot_date":"2026-07-10","constituent_code":"457190","constituent_name":"이수스페셜티케미컬","quantity":2.0,"valuation":120000.0,"weight":0.012247582879301487},{"snapshot_date":"2026-07-10","constituent_code":"028670","constituent_name":"팬오션","quantity":24.0,"valuation":120000.0,"weight":0.012247582879301487},{"snapshot_date":"2026-07-10","constituent_code":"011210","constituent_name":"현대위아","quantity":2.0,"valuation":118800.0,"weight":0.012125107050508472},{"snapshot_date":"2026-07-10","constituent_code":"112610","constituent_name":"씨에스윈드","quantity":3.0,"valuation":117600.0,"weight":0.012002631221715458},{"snapshot_date":"2026-07-10","constituent_code":"251270","constituent_name":"넷마블","quantity":3.0,"valuation":114750.0,"weight":0.011711751128332048},{"snapshot_date":"2026-07-10","constituent_code":"005850","constituent_name":"에스엘","quantity":2.0,"valuation":113000.0,"weight":0.011533140544675568},{"snapshot_date":"2026-07-10","constituent_code":"120110","constituent_name":"코오롱인더","quantity":2.0,"valuation":109000.0,"weight":0.011124887782032184},{"snapshot_date":"2026-07-10","constituent_code":"302440","constituent_name":"SK바이오사이언스","quantity":3.0,"valuation":108450.0,"weight":0.01106875302716872},{"snapshot_date":"2026-07-10","constituent_code":"007340","constituent_name":"DN오토모티브","quantity":3.0,"valuation":102300.0,"weight":0.010441064404604518},{"snapshot_date":"2026-07-10","constituent_code":"008930","constituent_name":"한미사이언스","quantity":3.0,"valuation":97350.0,"weight":0.00993585161083333},{"snapshot_date":"2026-07-10","constituent_code":"022100","constituent_name":"포스코DX","quantity":5.0,"valuation":96150.0,"weight":0.009813375782040317},{"snapshot_date":"2026-07-10","constituent_code":"456040","constituent_name":"OCI","quantity":1.0,"valuation":85900.0,"weight":0.008767228077766647},{"snapshot_date":"2026-07-10","constituent_code":"004000","constituent_name":"롯데정밀화학","quantity":2.0,"valuation":85900.0,"weight":0.008767228077766647},{"snapshot_date":"2026-07-10","constituent_code":"026960","constituent_name":"동서","quantity":3.0,"valuation":78750.0,"weight":0.0080374762645416},{"snapshot_date":"2026-07-10","constituent_code":"000240","constituent_name":"한국앤컴퍼니","quantity":3.0,"valuation":76350.0,"weight":0.007792524606955571},{"snapshot_date":"2026-07-10","constituent_code":"001800","constituent_name":"오리온홀딩스","quantity":3.0,"valuation":75450.0,"weight":0.00770066773536081},{"snapshot_date":"2026-07-10","constituent_code":"007070","constituent_name":"GS리테일","quantity":3.0,"valuation":75000.0,"weight":0.007654739299563429},{"snapshot_date":"2026-07-10","constituent_code":"073240","constituent_name":"금호타이어","quantity":12.0,"valuation":72000.0,"weight":0.0073485497275808925},{"snapshot_date":"2026-07-10","constituent_code":"000120","constituent_name":"CJ대한통운","quantity":1.0,"valuation":71900.0,"weight":0.007338343408514808},{"snapshot_date":"2026-07-10","constituent_code":"093370","constituent_name":"후성","quantity":6.0,"valuation":71040.0,"weight":0.00725056906454648},{"snapshot_date":"2026-07-10","constituent_code":"002790","constituent_name":"아모레퍼시픽홀딩스","quantity":3.0,"valuation":70500.0,"weight":0.0071954549415896235},{"snapshot_date":"2026-07-10","constituent_code":"185750","constituent_name":"종근당","quantity":1.0,"valuation":69800.0,"weight":0.007124010708127032},{"snapshot_date":"2026-07-10","constituent_code":"017960","constituent_name":"한국카본","quantity":3.0,"valuation":69750.0,"weight":0.0071189075485939895},{"snapshot_date":"2026-07-10","constituent_code":"004990","constituent_name":"롯데지주","quantity":3.0,"valuation":68850.0,"weight":0.007027050676999228},{"snapshot_date":"2026-07-10","constituent_code":"361610","constituent_name":"SK아이이테크놀로지","quantity":4.0,"valuation":64000.0,"weight":0.006532044202294127},{"snapshot_date":"2026-07-10","constituent_code":"192080","constituent_name":"더블유게임즈","quantity":1.0,"valuation":63700.0,"weight":0.006501425245095873},{"snapshot_date":"2026-07-10","constituent_code":"001430","constituent_name":"세아베스틸지주","quantity":2.0,"valuation":60700.0,"weight":0.006195235673113335},{"snapshot_date":"2026-07-10","constituent_code":"034230","constituent_name":"파라다이스","quantity":4.0,"valuation":48840.0,"weight":0.004984766231875705},{"snapshot_date":"2026-07-10","constituent_code":"069260","constituent_name":"TKG휴켐스","quantity":3.0,"valuation":48120.0,"weight":0.004911280734599896},{"snapshot_date":"2026-07-10","constituent_code":"000080","constituent_name":"하이트진로","quantity":3.0,"valuation":46200.0,"weight":0.004715319408531073},{"snapshot_date":"2026-07-10","constituent_code":"300720","constituent_name":"한일시멘트","quantity":3.0,"valuation":43980.0,"weight":0.004488739125263995},{"snapshot_date":"2026-07-10","constituent_code":"000210","constituent_name":"DL","quantity":1.0,"valuation":42500.0,"weight":0.004337685603085943},{"snapshot_date":"2026-07-10","constituent_code":"285130","constituent_name":"SK케미칼","quantity":1.0,"valuation":40800.0,"weight":0.0041641781789625056},{"snapshot_date":"2026-07-10","constituent_code":"000670","constituent_name":"영풍","quantity":1.0,"valuation":35850.0,"weight":0.0036589653851913195},{"snapshot_date":"2026-07-10","constituent_code":"009240","constituent_name":"한샘","quantity":1.0,"valuation":35200.0,"weight":0.00359262431126177},{"snapshot_date":"2026-07-10","constituent_code":"001680","constituent_name":"대상","quantity":2.0,"valuation":35040.0,"weight":0.0035762942007560345},{"snapshot_date":"2026-07-10","constituent_code":"003090","constituent_name":"대웅","quantity":2.0,"valuation":34060.0,"weight":0.0034762722739084054},{"snapshot_date":"2026-07-10","constituent_code":"006040","constituent_name":"동원산업","quantity":1.0,"valuation":33700.0,"weight":0.003439529525270501},{"snapshot_date":"2026-07-10","constituent_code":"005420","constituent_name":"코스모화학","quantity":3.0,"valuation":28530.0,"weight":0.0029118628295539285},{"snapshot_date":"2026-07-10","constituent_code":"014820","constituent_name":"동원시스템즈","quantity":1.0,"valuation":20100.0,"weight":0.0020514701322829993},{"snapshot_date":"2026-07-10","constituent_code":"137310","constituent_name":"에스디바이오센서","quantity":3.0,"valuation":18960.0,"weight":0.0019351180949296351},{"snapshot_date":"2026-07-10","constituent_code":"008730","constituent_name":"율촌화학","quantity":1.0,"valuation":14040.0,"weight":0.001432967196878274}],"top_changes":{"additions":[],"removals":[],"weight_changes":[{"snapshot_date":"2026-07-10","previous_snapshot_date":"2026-07-09","change_type":"비중확대","constituent_code":"000660","constituent_name":"SK하이닉스","previous_weight":12.342209923118327,"weight":12.940387817507307,"weight_delta":0.5981778943889804,"active_signal_ratio":1.0,"active_change_type":"drift"},{"snapshot_date":"2026-07-10","previous_snapshot_date":"2026-07-09","change_type":"비중확대","constituent_code":"402340","constituent_name":"SK스퀘어","previous_weight":1.1716120143283044,"weight":1.2189406860624805,"weight_delta":0.0473286717341761,"active_signal_ratio":1.0,"active_change_type":"drift"},{"snapshot_date":"2026-07-10","previous_snapshot_date":"2026-07-09","change_type":"비중축소","constituent_code":"005930","constituent_name":"삼성전자","previous_weight":13.795654591287024,"weight":13.761179996801829,"weight_delta":-0.03447459448519474,"active_signal_ratio":1.0,"active_change_type":"drift"},{"snapshot_date":"2026-07-10","previous_snapshot_date":"2026-07-09","change_type":"비중축소","constituent_code":"000270","constituent_name":"기아","previous_weight":0.41788520210093016,"weight":0.384247500199952,"weight_delta":-0.033637701900978145,"active_signal_ratio":1.0,"active_change_type":"drift"},{"snapshot_date":"2026-07-10","previous_snapshot_date":"2026-07-09","change_type":"비중축소","constituent_code":"012450","constituent_name":"한화에어로스페이스","previous_weight":0.32011761336371786,"weight":0.29179866209935795,"weight_delta":-0.028318951264359904,"active_signal_ratio":1.0,"active_change_type":"drift"}]}},"2026-07-13":{"ticker":"0192S0","snapshot_date":"2026-07-13","kpis":{"snapshot_date":"2026-07-13","holding_count":186,"total_valuation":422302155.0,"total_weight":42.583465531143496,"top_holding":{"etf_idx":"K55210EU9643","ticker":"0192S0","etf_name":"SOL 코스피200채권혼합50","source_url":"https://www.funetf.co.kr/product/etf/view/KR70192S0000","snapshot_date":"2026-07-13","constituent_code":"005930","constituent_name":"삼성전자","quantity":485.0,"valuation":138225000.0,"weight":13.938123339773888}},"holdings":[{"snapshot_date":"2026-07-13","constituent_code":"005930","constituent_name":"삼성전자","quantity":485.0,"valuation":138225000.0,"weight":13.938123339773888},{"snapshot_date":"2026-07-13","constituent_code":"000660","constituent_name":"SK하이닉스","quantity":58.0,"valuation":126440000.0,"weight":12.749765346941656},{"snapshot_date":"2026-07-13","constituent_code":"402340","constituent_name":"SK스퀘어","quantity":9.0,"valuation":12681000.0,"weight":1.2787074846928752},{"snapshot_date":"2026-07-13","constituent_code":"009150","constituent_name":"삼성전기","quantity":6.0,"valuation":9504000.0,"weight":0.958349967236108},{"snapshot_date":"2026-07-13","constituent_code":"005380","constituent_name":"현대차","quantity":14.0,"valuation":6405000.0,"weight":0.6458576957225665},{"snapshot_date":"2026-07-13","constituent_code":"105560","constituent_name":"KB금융","quantity":31.0,"valuation":5716400.0,"weight":0.5764216911519874},{"snapshot_date":"2026-07-13","constituent_code":"055550","constituent_name":"신한지주","quantity":43.0,"valuation":4695600.0,"weight":0.47348780578218314},{"snapshot_date":"2026-07-13","constituent_code":"028260","constituent_name":"삼성물산","quantity":10.0,"valuation":3915000.0,"weight":0.39477484445805583},{"snapshot_date":"2026-07-13","constituent_code":"000270","constituent_name":"기아","quantity":26.0,"valuation":3835000.0,"weight":0.386707925541927},{"snapshot_date":"2026-07-13","constituent_code":"034020","constituent_name":"두산에너빌리티","quantity":45.0,"valuation":3514500.0,"weight":0.35438983163418575},{"snapshot_date":"2026-07-13","constituent_code":"012330","constituent_name":"현대모비스","quantity":7.0,"valuation":3416000.0,"weight":0.34445743771870213},{"snapshot_date":"2026-07-13","constituent_code":"086790","constituent_name":"하나금융지주","quantity":26.0,"valuation":3341000.0,"weight":0.3368947012348313},{"snapshot_date":"2026-07-13","constituent_code":"032830","constituent_name":"삼성생명","quantity":9.0,"valuation":3064500.0,"weight":0.30901341273096095},{"snapshot_date":"2026-07-13","constituent_code":"298040","constituent_name":"효성중공업","quantity":1.0,"valuation":2924000.0,"weight":0.29484588638450965},{"snapshot_date":"2026-07-13","constituent_code":"012450","constituent_name":"한화에어로스페이스","quantity":3.0,"valuation":2901000.0,"weight":0.2925266471961226},{"snapshot_date":"2026-07-13","constituent_code":"068270","constituent_name":"셀트리온","quantity":16.0,"valuation":2803200.0,"weight":0.28266483882115506},{"snapshot_date":"2026-07-13","constituent_code":"035420","constituent_name":"네이버/NAVER","quantity":14.0,"valuation":2678200.0,"weight":0.2700602780147037},{"snapshot_date":"2026-07-13","constituent_code":"006400","constituent_name":"삼성SDI","quantity":6.0,"valuation":2604000.0,"weight":0.2625782107199942},{"snapshot_date":"2026-07-13","constituent_code":"267260","constituent_name":"HD현대일렉트릭","quantity":3.0,"valuation":2553000.0,"weight":0.25743554991096207},{"snapshot_date":"2026-07-13","constituent_code":"316140","constituent_name":"우리금융지주","quantity":70.0,"valuation":2201500.0,"weight":0.22199152492322094},{"snapshot_date":"2026-07-13","constituent_code":"005490","constituent_name":"POSCO홀딩스/포스코홀딩스","quantity":7.0,"valuation":2194500.0,"weight":0.22128566951805967},{"snapshot_date":"2026-07-13","constituent_code":"066570","constituent_name":"LG전자","quantity":11.0,"valuation":2006400.0,"weight":0.20231832641651168},{"snapshot_date":"2026-07-13","constituent_code":"034730","constituent_name":"SK","quantity":3.0,"valuation":1971000.0,"weight":0.19874871479612466},{"snapshot_date":"2026-07-13","constituent_code":"000810","constituent_name":"삼성화재","quantity":3.0,"valuation":1944000.0,"weight":0.19602612966193117},{"snapshot_date":"2026-07-13","constituent_code":"010120","constituent_name":"LS ELECTRIC","quantity":9.0,"valuation":1822500.0,"weight":0.18377449655806047},{"snapshot_date":"2026-07-13","constituent_code":"009540","constituent_name":"HD한국조선해양","quantity":5.0,"valuation":1702500.0,"weight":0.17167411818386719},{"snapshot_date":"2026-07-13","constituent_code":"373220","constituent_name":"LG에너지솔루션","quantity":5.0,"valuation":1630000.0,"weight":0.16436347291612544},{"snapshot_date":"2026-07-13","constituent_code":"033780","constituent_name":"KT&G","quantity":9.0,"valuation":1561500.0,"weight":0.1574561735941901},{"snapshot_date":"2026-07-13","constituent_code":"010140","constituent_name":"삼성중공업","quantity":69.0,"valuation":1542150.0,"weight":0.15550498758135142},{"snapshot_date":"2026-07-13","constituent_code":"329180","constituent_name":"HD현대중공업","quantity":3.0,"valuation":1512000.0,"weight":0.15246476751483537},{"snapshot_date":"2026-07-13","constituent_code":"079550","constituent_name":"LIG디펜스앤에어로스페이스","quantity":2.0,"valuation":1498000.0,"weight":0.1510530567045128},{"snapshot_date":"2026-07-13","constituent_code":"011070","constituent_name":"LG이노텍","quantity":2.0,"valuation":1484000.0,"weight":0.14964134589419026},{"snapshot_date":"2026-07-13","constituent_code":"064350","constituent_name":"현대로템","quantity":8.0,"valuation":1431200.0,"weight":0.14431717940954522},{"snapshot_date":"2026-07-13","constituent_code":"207940","constituent_name":"삼성바이오로직스","quantity":1.0,"valuation":1395000.0,"weight":0.1406668985999969},{"snapshot_date":"2026-07-13","constituent_code":"000150","constituent_name":"두산","quantity":1.0,"valuation":1382000.0,"weight":0.13935602427612598},{"snapshot_date":"2026-07-13","constituent_code":"017670","constituent_name":"SK텔레콤","quantity":15.0,"valuation":1330500.0,"weight":0.134162945223868},{"snapshot_date":"2026-07-13","constituent_code":"051910","constituent_name":"LG화학","quantity":5.0,"valuation":1320000.0,"weight":0.1331041621161261},{"snapshot_date":"2026-07-13","constituent_code":"030200","constituent_name":"KT","quantity":23.0,"valuation":1246600.0,"weight":0.1257027640105779},{"snapshot_date":"2026-07-13","constituent_code":"035720","constituent_name":"카카오","quantity":35.0,"valuation":1237250.0,"weight":0.12475994286225532},{"snapshot_date":"2026-07-13","constituent_code":"015760","constituent_name":"한국전력","quantity":33.0,"valuation":1194600.0,"weight":0.12045926671509413},{"snapshot_date":"2026-07-13","constituent_code":"006800","constituent_name":"미래에셋증권","quantity":28.0,"valuation":1181600.0,"weight":0.11914839239122318},{"snapshot_date":"2026-07-13","constituent_code":"047810","constituent_name":"한국항공우주","quantity":8.0,"valuation":1154400.0,"weight":0.11640563995973938},{"snapshot_date":"2026-07-13","constituent_code":"042660","constituent_name":"한화오션","quantity":14.0,"valuation":1138200.0,"weight":0.11477208887922329},{"snapshot_date":"2026-07-13","constituent_code":"278470","constituent_name":"에이피알","quantity":3.0,"valuation":1125000.0,"weight":0.11344104725806202},{"snapshot_date":"2026-07-13","constituent_code":"010130","constituent_name":"고려아연","quantity":1.0,"valuation":1043000.0,"weight":0.10517245536902994},{"snapshot_date":"2026-07-13","constituent_code":"267250","constituent_name":"HD현대","quantity":5.0,"valuation":997500.0,"weight":0.10058439523548167},{"snapshot_date":"2026-07-13","constituent_code":"071050","constituent_name":"한국금융지주","quantity":4.0,"valuation":956000.0,"weight":0.09639968104773981},{"snapshot_date":"2026-07-13","constituent_code":"138040","constituent_name":"메리츠금융지주","quantity":8.0,"valuation":920000.0,"weight":0.09276956753548184},{"snapshot_date":"2026-07-13","constituent_code":"003550","constituent_name":"LG","quantity":9.0,"valuation":911700.0,"weight":0.09193262469793347},{"snapshot_date":"2026-07-13","constituent_code":"042700","constituent_name":"한미반도체","quantity":4.0,"valuation":888000.0,"weight":0.08954279996903029},{"snapshot_date":"2026-07-13","constituent_code":"000720","constituent_name":"현대건설","quantity":8.0,"valuation":857600.0,"weight":0.08647737078090133},{"snapshot_date":"2026-07-13","constituent_code":"323410","constituent_name":"카카오뱅크","quantity":36.0,"valuation":824400.0,"weight":0.08312959943070786},{"snapshot_date":"2026-07-13","constituent_code":"096770","constituent_name":"SK이노베이션","quantity":8.0,"valuation":823200.0,"weight":0.08300859564696592},{"snapshot_date":"2026-07-13","constituent_code":"018260","constituent_name":"삼성에스디에스","quantity":4.0,"valuation":798400.0,"weight":0.08050785078296598},{"snapshot_date":"2026-07-13","constituent_code":"086280","constituent_name":"현대글로비스","quantity":4.0,"valuation":766400.0,"weight":0.07728108321651443},{"snapshot_date":"2026-07-13","constituent_code":"259960","constituent_name":"크래프톤","quantity":3.0,"valuation":714000.0,"weight":0.07199725132645003},{"snapshot_date":"2026-07-13","constituent_code":"028050","constituent_name":"삼성E&A","quantity":16.0,"valuation":705600.0,"weight":0.0711502248402565},{"snapshot_date":"2026-07-13","constituent_code":"003490","constituent_name":"대한항공","quantity":26.0,"valuation":695500.0,"weight":0.07013177632709523},{"snapshot_date":"2026-07-13","constituent_code":"180640","constituent_name":"한진칼","quantity":5.0,"valuation":673500.0,"weight":0.0679133736251598},{"snapshot_date":"2026-07-13","constituent_code":"016360","constituent_name":"삼성증권","quantity":6.0,"valuation":672000.0,"weight":0.06776211889548238},{"snapshot_date":"2026-07-13","constituent_code":"039490","constituent_name":"키움증권","quantity":2.0,"valuation":672000.0,"weight":0.06776211889548238},{"snapshot_date":"2026-07-13","constituent_code":"352820","constituent_name":"하이브","quantity":3.0,"valuation":661500.0,"weight":0.06670333578774047},{"snapshot_date":"2026-07-13","constituent_code":"006260","constituent_name":"LS","quantity":2.0,"valuation":658000.0,"weight":0.06635040808515984},{"snapshot_date":"2026-07-13","constituent_code":"011200","constituent_name":"HMM","quantity":32.0,"valuation":631680.0,"weight":0.06369639176175344},{"snapshot_date":"2026-07-13","constituent_code":"004170","constituent_name":"신세계","quantity":1.0,"valuation":629000.0,"weight":0.06342614997806312},{"snapshot_date":"2026-07-13","constituent_code":"005830","constituent_name":"DB손해보험","quantity":4.0,"valuation":623200.0,"weight":0.06284129835664379},{"snapshot_date":"2026-07-13","constituent_code":"007660","constituent_name":"이수페타시스","quantity":6.0,"valuation":622800.0,"weight":0.06280096376206314},{"snapshot_date":"2026-07-13","constituent_code":"024110","constituent_name":"기업은행","quantity":28.0,"valuation":595000.0,"weight":0.05999770943870836},{"snapshot_date":"2026-07-13","constituent_code":"272210","constituent_name":"한화시스템","quantity":8.0,"valuation":573600.0,"weight":0.05783980862864389},{"snapshot_date":"2026-07-13","constituent_code":"161390","constituent_name":"한국타이어앤테크놀로지","quantity":8.0,"valuation":572000.0,"weight":0.057678470250321315},{"snapshot_date":"2026-07-13","constituent_code":"021240","constituent_name":"코웨이","quantity":6.0,"valuation":539400.0,"weight":0.05439120079199881},{"snapshot_date":"2026-07-13","constituent_code":"010950","constituent_name":"S-Oil","quantity":4.0,"valuation":528400.0,"weight":0.05328199944103109},{"snapshot_date":"2026-07-13","constituent_code":"138930","constituent_name":"BNK금융지주","quantity":28.0,"valuation":499800.0,"weight":0.05039807592851502},{"snapshot_date":"2026-07-13","constituent_code":"036570","constituent_name":"엔씨소프트/NC소프트","quantity":2.0,"valuation":497000.0,"weight":0.05011573376645051},{"snapshot_date":"2026-07-13","constituent_code":"005940","constituent_name":"NH투자증권","quantity":15.0,"valuation":474000.0,"weight":0.04779649457806347},{"snapshot_date":"2026-07-13","constituent_code":"003670","constituent_name":"포스코퓨처엠","quantity":3.0,"valuation":455400.0,"weight":0.04592093593006351},{"snapshot_date":"2026-07-13","constituent_code":"002380","constituent_name":"KCC","quantity":1.0,"valuation":453500.0,"weight":0.045729346605805445},{"snapshot_date":"2026-07-13","constituent_code":"307950","constituent_name":"현대오토에버","quantity":1.0,"valuation":452000.0,"weight":0.04557809187612803},{"snapshot_date":"2026-07-13","constituent_code":"009830","constituent_name":"한화솔루션","quantity":14.0,"valuation":446600.0,"weight":0.04503357484928933},{"snapshot_date":"2026-07-13","constituent_code":"032640","constituent_name":"LG유플러스","quantity":29.0,"valuation":433840.0,"weight":0.04374690128216678},{"snapshot_date":"2026-07-13","constituent_code":"175330","constituent_name":"JB금융지주","quantity":16.0,"valuation":416800.0,"weight":0.04202864755303134},{"snapshot_date":"2026-07-13","constituent_code":"271560","constituent_name":"오리온","quantity":3.0,"valuation":411300.0,"weight":0.04147404687754748},{"snapshot_date":"2026-07-13","constituent_code":"000100","constituent_name":"유한양행","quantity":6.0,"valuation":411000.0,"weight":0.041443795931611994},{"snapshot_date":"2026-07-13","constituent_code":"078930","constituent_name":"GS","quantity":5.0,"valuation":401000.0,"weight":0.040435431067095885},{"snapshot_date":"2026-07-13","constituent_code":"010060","constituent_name":"OCI홀딩스","quantity":2.0,"valuation":395600.0,"weight":0.039890914040257186},{"snapshot_date":"2026-07-13","constituent_code":"443060","constituent_name":"HD현대마린솔루션","quantity":2.0,"valuation":394400.0,"weight":0.03976991025651526},{"snapshot_date":"2026-07-13","constituent_code":"001440","constituent_name":"대한전선","quantity":13.0,"valuation":393250.0,"weight":0.039653948297095905},{"snapshot_date":"2026-07-13","constituent_code":"267270","constituent_name":"HD건설기계","quantity":3.0,"valuation":390900.0,"weight":0.03941698255393462},{"snapshot_date":"2026-07-13","constituent_code":"128940","constituent_name":"한미약품","quantity":1.0,"valuation":389000.0,"weight":0.03922539322967656},{"snapshot_date":"2026-07-13","constituent_code":"0126Z0","constituent_name":"삼성에피스홀딩스","quantity":1.0,"valuation":384500.0,"weight":0.03877162904064431},{"snapshot_date":"2026-07-13","constituent_code":"062040","constituent_name":"산일전기","quantity":2.0,"valuation":378200.0,"weight":0.03813635917599916},{"snapshot_date":"2026-07-13","constituent_code":"090430","constituent_name":"아모레퍼시픽","quantity":3.0,"valuation":369300.0,"weight":0.03723891444657983},{"snapshot_date":"2026-07-13","constituent_code":"000990","constituent_name":"DB하이텍","quantity":3.0,"valuation":365700.0,"weight":0.03687590309535403},{"snapshot_date":"2026-07-13","constituent_code":"034220","constituent_name":"LG디스플레이","quantity":33.0,"valuation":363330.0,"weight":0.03663692062246371},{"snapshot_date":"2026-07-13","constituent_code":"064400","constituent_name":"LG씨앤에스/LGCNS","quantity":5.0,"valuation":355500.0,"weight":0.0358473709335476},{"snapshot_date":"2026-07-13","constituent_code":"047040","constituent_name":"대우건설","quantity":20.0,"valuation":349000.0,"weight":0.03519193377161213},{"snapshot_date":"2026-07-13","constituent_code":"326030","constituent_name":"SK바이오팜","quantity":4.0,"valuation":329600.0,"weight":0.03323570593445088},{"snapshot_date":"2026-07-13","constituent_code":"241560","constituent_name":"두산밥캣","quantity":5.0,"valuation":314500.0,"weight":0.03171307498903156},{"snapshot_date":"2026-07-13","constituent_code":"066970","constituent_name":"엘앤에프","quantity":3.0,"valuation":301500.0,"weight":0.030402200665160622},{"snapshot_date":"2026-07-13","constituent_code":"001040","constituent_name":"CJ","quantity":2.0,"valuation":284400.0,"weight":0.02867789674683808},{"snapshot_date":"2026-07-13","constituent_code":"011790","constituent_name":"SKC","quantity":3.0,"valuation":283800.0,"weight":0.028617394854967112},{"snapshot_date":"2026-07-13","constituent_code":"000880","constituent_name":"한화","quantity":3.0,"valuation":280800.0,"weight":0.02831488539561228},{"snapshot_date":"2026-07-13","constituent_code":"082740","constituent_name":"한화엔진","quantity":6.0,"valuation":279600.0,"weight":0.02819388161187035},{"snapshot_date":"2026-07-13","constituent_code":"111770","constituent_name":"영원무역","quantity":3.0,"valuation":261000.0,"weight":0.02631832296387039},{"snapshot_date":"2026-07-13","constituent_code":"139130","constituent_name":"iM금융지주","quantity":14.0,"valuation":249900.0,"weight":0.02519903796425751},{"snapshot_date":"2026-07-13","constituent_code":"014680","constituent_name":"한솔케미칼","quantity":1.0,"valuation":248500.0,"weight":0.025057866883225255},{"snapshot_date":"2026-07-13","constituent_code":"047050","constituent_name":"포스코인터내셔널","quantity":5.0,"valuation":247500.0,"weight":0.024957030396773647},{"snapshot_date":"2026-07-13","constituent_code":"051900","constituent_name":"LG생활건강","quantity":1.0,"valuation":245000.0,"weight":0.02470493918064462},{"snapshot_date":"2026-07-13","constituent_code":"004020","constituent_name":"현대제철","quantity":9.0,"valuation":242100.0,"weight":0.024412513369934948},{"snapshot_date":"2026-07-13","constituent_code":"011780","constituent_name":"금호석유화학","quantity":2.0,"valuation":234800.0,"weight":0.02367640701883819},{"snapshot_date":"2026-07-13","constituent_code":"001450","constituent_name":"현대해상","quantity":6.0,"valuation":228900.0,"weight":0.023081471748773688},{"snapshot_date":"2026-07-13","constituent_code":"454910","constituent_name":"두산로보틱스","quantity":3.0,"valuation":223500.0,"weight":0.02253695472193499},{"snapshot_date":"2026-07-13","constituent_code":"012750","constituent_name":"에스원","quantity":3.0,"valuation":219000.0,"weight":0.022083190532902742},{"snapshot_date":"2026-07-13","constituent_code":"161890","constituent_name":"한국콜마","quantity":2.0,"valuation":213000.0,"weight":0.021478171614193076},{"snapshot_date":"2026-07-13","constituent_code":"017800","constituent_name":"현대엘리베이터","quantity":3.0,"valuation":208500.0,"weight":0.02102440742516083},{"snapshot_date":"2026-07-13","constituent_code":"052690","constituent_name":"한전기술","quantity":2.0,"valuation":204400.0,"weight":0.020610977830709226},{"snapshot_date":"2026-07-13","constituent_code":"483650","constituent_name":"달바글로벌","quantity":1.0,"valuation":197900.0,"weight":0.019955540668773756},{"snapshot_date":"2026-07-13","constituent_code":"097950","constituent_name":"CJ제일제당","quantity":1.0,"valuation":191000.0,"weight":0.01925976891225764},{"snapshot_date":"2026-07-13","constituent_code":"375500","constituent_name":"DL이앤씨","quantity":3.0,"valuation":189900.0,"weight":0.01914884877716087},{"snapshot_date":"2026-07-13","constituent_code":"009970","constituent_name":"영원무역홀딩스","quantity":1.0,"valuation":189300.0,"weight":0.019088346885289903},{"snapshot_date":"2026-07-13","constituent_code":"071970","constituent_name":"HD현대마린엔진","quantity":3.0,"valuation":184800.0,"weight":0.018634582696257656},{"snapshot_date":"2026-07-13","constituent_code":"035250","constituent_name":"강원랜드","quantity":12.0,"valuation":175320.0,"weight":0.017678652804696385},{"snapshot_date":"2026-07-13","constituent_code":"192820","constituent_name":"코스맥스","quantity":1.0,"valuation":172700.0,"weight":0.017414461210193168},{"snapshot_date":"2026-07-13","constituent_code":"009420","constituent_name":"한올바이오파마","quantity":3.0,"valuation":172200.0,"weight":0.01736404296696736},{"snapshot_date":"2026-07-13","constituent_code":"069960","constituent_name":"현대백화점","quantity":1.0,"valuation":167100.0,"weight":0.016849776886064146},{"snapshot_date":"2026-07-13","constituent_code":"139480","constituent_name":"이마트","quantity":2.0,"valuation":163600.0,"weight":0.016496849183483507},{"snapshot_date":"2026-07-13","constituent_code":"088350","constituent_name":"한화생명","quantity":35.0,"valuation":162750.0,"weight":0.016411138169999638},{"snapshot_date":"2026-07-13","constituent_code":"377300","constituent_name":"카카오페이","quantity":4.0,"valuation":155400.0,"weight":0.015669989994580302},{"snapshot_date":"2026-07-13","constituent_code":"023530","constituent_name":"롯데쇼핑","quantity":1.0,"valuation":155300.0,"weight":0.01565990634593514},{"snapshot_date":"2026-07-13","constituent_code":"383220","constituent_name":"F&F","quantity":2.0,"valuation":155200.0,"weight":0.01564982269728998},{"snapshot_date":"2026-07-13","constituent_code":"450080","constituent_name":"에코프로머티","quantity":4.0,"valuation":152400.0,"weight":0.01536748053522547},{"snapshot_date":"2026-07-13","constituent_code":"008770","constituent_name":"호텔신라","quantity":3.0,"valuation":151200.0,"weight":0.015246476751483537},{"snapshot_date":"2026-07-13","constituent_code":"030000","constituent_name":"제일기획","quantity":8.0,"valuation":150480.0,"weight":0.015173874481238376},{"snapshot_date":"2026-07-13","constituent_code":"204320","constituent_name":"HL만도","quantity":3.0,"valuation":148650.0,"weight":0.014989343711031928},{"snapshot_date":"2026-07-13","constituent_code":"029780","constituent_name":"삼성카드","quantity":3.0,"valuation":145200.0,"weight":0.014641457832773873},{"snapshot_date":"2026-07-13","constituent_code":"051600","constituent_name":"한전KPS","quantity":3.0,"valuation":137850.0,"weight":0.013900309657354533},{"snapshot_date":"2026-07-13","constituent_code":"081660","constituent_name":"미스토홀딩스","quantity":3.0,"valuation":133950.0,"weight":0.013507047360193251},{"snapshot_date":"2026-07-13","constituent_code":"018880","constituent_name":"한온시스템","quantity":37.0,"valuation":133385.0,"weight":0.013450074745348092},{"snapshot_date":"2026-07-13","constituent_code":"036460","constituent_name":"한국가스공사","quantity":4.0,"valuation":132200.0,"weight":0.013330583508902934},{"snapshot_date":"2026-07-13","constituent_code":"069620","constituent_name":"대웅제약","quantity":1.0,"valuation":131900.0,"weight":0.01330033256296745},{"snapshot_date":"2026-07-13","constituent_code":"103140","constituent_name":"풍산","quantity":2.0,"valuation":130200.0,"weight":0.013128910535999712},{"snapshot_date":"2026-07-13","constituent_code":"457190","constituent_name":"이수스페셜티케미컬","quantity":2.0,"valuation":126200.0,"weight":0.01272556459019327},{"snapshot_date":"2026-07-13","constituent_code":"028670","constituent_name":"팬오션","quantity":24.0,"valuation":126000.0,"weight":0.012705397292902947},{"snapshot_date":"2026-07-13","constituent_code":"011210","constituent_name":"현대위아","quantity":2.0,"valuation":123800.0,"weight":0.012483557022709403},{"snapshot_date":"2026-07-13","constituent_code":"282330","constituent_name":"BGF리테일","quantity":1.0,"valuation":123600.0,"weight":0.01246338972541908},{"snapshot_date":"2026-07-13","constituent_code":"011170","constituent_name":"롯데케미칼","quantity":2.0,"valuation":123600.0,"weight":0.01246338972541908},{"snapshot_date":"2026-07-13","constituent_code":"006280","constituent_name":"녹십자","quantity":1.0,"valuation":123200.0,"weight":0.012423055130838436},{"snapshot_date":"2026-07-13","constituent_code":"112610","constituent_name":"씨에스윈드","quantity":3.0,"valuation":119550.0,"weight":0.012055001955290058},{"snapshot_date":"2026-07-13","constituent_code":"251270","constituent_name":"넷마블","quantity":3.0,"valuation":112650.0,"weight":0.011359230198773945},{"snapshot_date":"2026-07-13","constituent_code":"120110","constituent_name":"코오롱인더","quantity":2.0,"valuation":111800.0,"weight":0.011273519185290074},{"snapshot_date":"2026-07-13","constituent_code":"005850","constituent_name":"에스엘","quantity":2.0,"valuation":111400.0,"weight":0.011233184590709431},{"snapshot_date":"2026-07-13","constituent_code":"302440","constituent_name":"SK바이오사이언스","quantity":3.0,"valuation":109950.0,"weight":0.011086971685354595},{"snapshot_date":"2026-07-13","constituent_code":"007340","constituent_name":"DN오토모티브","quantity":3.0,"valuation":107550.0,"weight":0.01084496411787073},{"snapshot_date":"2026-07-13","constituent_code":"022100","constituent_name":"포스코DX","quantity":5.0,"valuation":101000.0,"weight":0.01018448513161268},{"snapshot_date":"2026-07-13","constituent_code":"008930","constituent_name":"한미사이언스","quantity":3.0,"valuation":100200.0,"weight":0.010103815942451392},{"snapshot_date":"2026-07-13","constituent_code":"073240","constituent_name":"금호타이어","quantity":12.0,"valuation":93600.0,"weight":0.00943829513187076},{"snapshot_date":"2026-07-13","constituent_code":"004000","constituent_name":"롯데정밀화학","quantity":2.0,"valuation":90300.0,"weight":0.009105534726580445},{"snapshot_date":"2026-07-13","constituent_code":"456040","constituent_name":"OCI","quantity":1.0,"valuation":89400.0,"weight":0.009014781888773995},{"snapshot_date":"2026-07-13","constituent_code":"093370","constituent_name":"후성","quantity":6.0,"valuation":82440.0,"weight":0.008312959943070785},{"snapshot_date":"2026-07-13","constituent_code":"001800","constituent_name":"오리온홀딩스","quantity":3.0,"valuation":80400.0,"weight":0.008107253510709499},{"snapshot_date":"2026-07-13","constituent_code":"007070","constituent_name":"GS리테일","quantity":3.0,"valuation":77850.0,"weight":0.007850120470257892},{"snapshot_date":"2026-07-13","constituent_code":"026960","constituent_name":"동서","quantity":3.0,"valuation":77700.0,"weight":0.007834994997290151},{"snapshot_date":"2026-07-13","constituent_code":"000240","constituent_name":"한국앤컴퍼니","quantity":3.0,"valuation":75150.0,"weight":0.007577861956838543},{"snapshot_date":"2026-07-13","constituent_code":"000120","constituent_name":"CJ대한통운","quantity":1.0,"valuation":73900.0,"weight":0.00745181634877403},{"snapshot_date":"2026-07-13","constituent_code":"017960","constituent_name":"한국카본","quantity":3.0,"valuation":73350.0,"weight":0.007396356281225644},{"snapshot_date":"2026-07-13","constituent_code":"002790","constituent_name":"아모레퍼시픽홀딩스","quantity":3.0,"valuation":72900.0,"weight":0.007350979862322419},{"snapshot_date":"2026-07-13","constituent_code":"004990","constituent_name":"롯데지주","quantity":3.0,"valuation":70200.0,"weight":0.00707872134890307},{"snapshot_date":"2026-07-13","constituent_code":"185750","constituent_name":"종근당","quantity":1.0,"valuation":70200.0,"weight":0.00707872134890307},{"snapshot_date":"2026-07-13","constituent_code":"001430","constituent_name":"세아베스틸지주","quantity":2.0,"valuation":63600.0,"weight":0.0064132005383224396},{"snapshot_date":"2026-07-13","constituent_code":"192080","constituent_name":"더블유게임즈","quantity":1.0,"valuation":61800.0,"weight":0.00623169486270954},{"snapshot_date":"2026-07-13","constituent_code":"361610","constituent_name":"SK아이이테크놀로지","quantity":4.0,"valuation":59600.0,"weight":0.0060098545925159974},{"snapshot_date":"2026-07-13","constituent_code":"034230","constituent_name":"파라다이스","quantity":4.0,"valuation":50640.0,"weight":0.005106359673909565},{"snapshot_date":"2026-07-13","constituent_code":"069260","constituent_name":"TKG휴켐스","quantity":3.0,"valuation":46320.0,"weight":0.004670746052438607},{"snapshot_date":"2026-07-13","constituent_code":"000210","constituent_name":"DL","quantity":1.0,"valuation":45650.0,"weight":0.004603185606516028},{"snapshot_date":"2026-07-13","constituent_code":"000080","constituent_name":"하이트진로","quantity":3.0,"valuation":45120.0,"weight":0.004549742268696674},{"snapshot_date":"2026-07-13","constituent_code":"300720","constituent_name":"한일시멘트","quantity":3.0,"valuation":44370.0,"weight":0.004474114903857966},{"snapshot_date":"2026-07-13","constituent_code":"285130","constituent_name":"SK케미칼","quantity":1.0,"valuation":40700.0,"weight":0.004104044998580555},{"snapshot_date":"2026-07-13","constituent_code":"000670","constituent_name":"영풍","quantity":1.0,"valuation":36750.0,"weight":0.003705740877096693},{"snapshot_date":"2026-07-13","constituent_code":"001680","constituent_name":"대상","quantity":2.0,"valuation":34880.0,"weight":0.0035171766474321807},{"snapshot_date":"2026-07-13","constituent_code":"009240","constituent_name":"한샘","quantity":1.0,"valuation":34800.0,"weight":0.003509109728516052},{"snapshot_date":"2026-07-13","constituent_code":"006040","constituent_name":"동원산업","quantity":1.0,"valuation":34550.0,"weight":0.003483900606903149},{"snapshot_date":"2026-07-13","constituent_code":"003090","constituent_name":"대웅","quantity":2.0,"valuation":34060.0,"weight":0.00343449072854186},{"snapshot_date":"2026-07-13","constituent_code":"005420","constituent_name":"코스모화학","quantity":3.0,"valuation":30030.0,"weight":0.003028119688141869},{"snapshot_date":"2026-07-13","constituent_code":"014820","constituent_name":"동원시스템즈","quantity":1.0,"valuation":20100.0,"weight":0.0020268133776773748},{"snapshot_date":"2026-07-13","constituent_code":"137310","constituent_name":"에스디바이오센서","quantity":3.0,"valuation":19380.0,"weight":0.001954211107432215},{"snapshot_date":"2026-07-13","constituent_code":"008730","constituent_name":"율촌화학","quantity":1.0,"valuation":14630.0,"weight":0.0014752377967870644}],"top_changes":{"additions":[],"removals":[],"weight_changes":[{"snapshot_date":"2026-07-13","previous_snapshot_date":"2026-07-10","change_type":"비중축소","constituent_code":"000660","constituent_name":"SK하이닉스","previous_weight":12.940387817507307,"weight":12.749765346941656,"weight_delta":-0.19062247056565162,"active_signal_ratio":1.0,"active_change_type":"drift"},{"snapshot_date":"2026-07-13","previous_snapshot_date":"2026-07-10","change_type":"비중확대","constituent_code":"005930","constituent_name":"삼성전자","previous_weight":13.761179996801829,"weight":13.938123339773888,"weight_delta":0.17694334297205927,"active_signal_ratio":1.0,"active_change_type":"drift"},{"snapshot_date":"2026-07-13","previous_snapshot_date":"2026-07-10","change_type":"비중확대","constituent_code":"402340","constituent_name":"SK스퀘어","previous_weight":1.2189406860624805,"weight":1.2787074846928752,"weight_delta":0.05976679863039469,"active_signal_ratio":1.0,"active_change_type":"drift"}]}}}}
